{"type": "FeatureCollection", "features": [{"type": "Feature", "properties": {"danger_level": 2}, "geometry": {"type": "Polygon", "coordinates": [[[9.007456413280238, 47.18370132835671], [9.007456413280238, 47.18370132835671]]]}}, {"type": "Feature", "properties": {"danger_level": 2}, "geometry": {"type": "Polygon", "coordinates": [[[9.314489218465873, 47.180950857175475], [9.314489218465873, 47.180950857175475]]]}}, {"type": "Feature", "properties": {"danger_level": 2}, "geometry": {"type": "Polygon", "coordinates": [[[9.330370225630647, 47.18080859142472], [9.330370225630647, 47.18080859142472]]]}}, {"type": "Feature", "properties": {"danger_level": 2}, "geometry": {"type": "Polygon", "coordinates": [[[9.033817273994163, 47.17976568595282], [9.033817273994163, 47.17976568595282]]]}}, {"type": "Feature", "properties": {"danger_level": 2}, "geometry": {"type": "Polygon", "coordinates": [[[9.254216652208397, 47.11120037469493], [9.254216652208397, 47.11120037469493]]]}}, {"type": "Feature", "properties": {"danger_level": 2}, "geometry": {"type": "Polygon", "coordinates": [[[9.480017184038259, 47.046286174339414], [9.480017184038259, 47.046286174339414]]]}}, {"type": "Feature", "properties": {"danger_level": 2}, "geometry": {"type": "Polygon", "coordinates": [[[9.496328129445835, 47.060938039865846], [9.496328129445835, 47.060938039865846]]]}}, {"type": "Feature", "properties": {"danger_level": 2}, "geometry": {"type": "Polygon", "coordinates": [[[9.665510570082025, 47.052023472885885], [9.665510570082025, 47.052023472885885]]]}}, {"type": "Feature", "properties": {"danger_level": 2}, "geometry": {"type": "Polygon", "coordinates": [[[8.304285231041467, 47.0383211757987], [8.304285231041467, 47.0383211757987]]]}}, {"type": "Feature", "properties": {"danger_level": 2}, "geometry": {"type": "Polygon", "coordinates": [[[8.588746060718298, 46.98767946563427], [8.588746060718298, 46.98767946563427]]]}}, {"type": "Feature", "properties": {"danger_level": 2}, "geometry": {"type": "Polygon", "coordinates": [[[9.858474241975335, 46.950408475838906], [9.858474241975335, 46.950408475838906]]]}}, {"type": "Feature", "properties": {"danger_level": 2}, "geometry": {"type": "Polygon", "coordinates": [[[10.29763380441269, 46.93907539109613], [10.29763380441269, 46.93907539109613]]]}}, {"type": "Feature", "properties": {"danger_level": 2}, "geometry": {"type": "Polygon", "coordinates": [[[10.455798968696232, 46.91546153667281], [10.455798968696232, 46.91546153667281]]]}}, {"type": "Feature", "properties": {"danger_level": 2}, "geometry": {"type": "Polygon", "coordinates": [[[9.952577954796281, 46.90887102032212], [9.952577954796281, 46.90887102032212]]]}}, {"type": "Feature", "properties": {"danger_level": 2}, "geometry": {"type": "Polygon", "coordinates": [[[10.44413678497938, 46.878571052313674], [10.44413678497938, 46.878571052313674]]]}}, {"type": "Feature", "properties": {"danger_level": 2}, "geometry": {"type": "Polygon", "coordinates": [[[10.216294046496216, 46.87321312910255], [10.216294046496216, 46.87321312910255]]]}}, {"type": "Feature", "properties": {"danger_level": 2}, "geometry": {"type": "Polygon", "coordinates": [[[9.453898218026353, 46.876343352319424], [9.453898218026353, 46.876343352319424]]]}}, {"type": "Feature", "properties": {"danger_level": 2}, "geometry": {"type": "Polygon", "coordinates": [[[9.538596922905148, 46.87558460164874], [9.538596922905148, 46.87558460164874]]]}}, {"type": "Feature", "properties": {"danger_level": 2}, "geometry": {"type": "Polygon", "coordinates": [[[9.527902100234598, 46.87198091266328], [9.527902100234598, 46.87198091266328]]]}}, {"type": "Feature", "properties": {"danger_level": 2}, "geometry": {"type": "Polygon", "coordinates": [[[9.511483670266323, 46.853630514317544], [9.511483670266323, 46.853630514317544]]]}}, {"type": "Feature", "properties": {"danger_level": 2}, "geometry": {"type": "Polygon", "coordinates": [[[10.443169423933078, 46.845284256940005], [10.443169423933078, 46.845284256940005]]]}}, {"type": "Feature", "properties": {"danger_level": 2}, "geometry": {"type": "Polygon", "coordinates": [[[9.527257192870398, 46.8497897157475], [9.527257192870398, 46.8497897157475]]]}}, {"type": "Feature", "properties": {"danger_level": 2}, "geometry": {"type": "Polygon", "coordinates": [[[10.093679781747344, 46.844715570637284], [10.093679781747344, 46.844715570637284]]]}}, {"type": "Feature", "properties": {"danger_level": 2}, "geometry": {"type": "Polygon", "coordinates": [[[10.386685742880724, 46.72370689307238], [10.386685742880724, 46.72370689307238]]]}}, {"type": "Feature", "properties": {"danger_level": 2}, "geometry": {"type": "Polygon", "coordinates": [[[10.386363289198624, 46.71261129461449], [10.386363289198624, 46.71261129461449]]]}}, {"type": "Feature", "properties": {"danger_level": 2}, "geometry": {"type": "Polygon", "coordinates": [[[8.734093636697903, 46.70521573577708], [8.734093636697903, 46.70521573577708]]]}}, {"type": "Feature", "properties": {"danger_level": 2}, "geometry": {"type": "Polygon", "coordinates": [[[10.437150288533868, 46.638166419059374], [10.437150288533868, 46.638166419059374]]]}}, {"type": "Feature", "properties": {"danger_level": 2}, "geometry": {"type": "Polygon", "coordinates": [[[8.631794171683131, 46.64694022708978], [8.631794171683131, 46.64694022708978]]]}}, {"type": "Feature", "properties": {"danger_level": 2}, "geometry": {"type": "Polygon", "coordinates": [[[8.705905538452077, 46.64627632025292], [8.705905538452077, 46.64627632025292]]]}}, {"type": "Feature", "properties": {"danger_level": 2}, "geometry": {"type": "Polygon", "coordinates": [[[10.225188557215478, 46.6326662300975], [10.225188557215478, 46.6326662300975]]]}}, {"type": "Feature", "properties": {"danger_level": 2}, "geometry": {"type": "Polygon", "coordinates": [[[10.245825810631676, 46.61398387833334], [10.245825810631676, 46.61398387833334]]]}}, {"type": "Feature", "properties": {"danger_level": 2}, "geometry": {"type": "Polygon", "coordinates": [[[10.108082930642933, 46.611518315353905], [10.108082930642933, 46.611518315353905]]]}}, {"type": "Feature", "properties": {"danger_level": 2}, "geometry": {"type": "Polygon", "coordinates": [[[10.086263347059033, 46.58951680610579], [10.086263347059033, 46.58951680610579]]]}}, {"type": "Feature", "properties": {"danger_level": 2}, "geometry": {"type": "Polygon", "coordinates": [[[10.075353555267082, 46.57851605148174], [10.075353555267082, 46.57851605148174]]]}}, {"type": "Feature", "properties": {"danger_level": 2}, "geometry": {"type": "Polygon", "coordinates": [[[10.461361458033787, 46.56026012026955], [10.461361458033787, 46.56026012026955]]]}}, {"type": "Feature", "properties": {"danger_level": 2}, "geometry": {"type": "Polygon", "coordinates": [[[10.445050512626214, 46.545608254743115], [10.445050512626214, 46.545608254743115]]]}}, {"type": "Feature", "properties": {"danger_level": 2}, "geometry": {"type": "Polygon", "coordinates": [[[10.036470634350705, 46.51597294697211], [10.036470634350705, 46.51597294697211]]]}}, {"type": "Feature", "properties": {"danger_level": 2}, "geometry": {"type": "Polygon", "coordinates": [[[9.823863995668116, 46.48828156109446], [9.823863995668116, 46.48828156109446]]]}}, {"type": "Feature", "properties": {"danger_level": 2}, "geometry": {"type": "Polygon", "coordinates": [[[9.310378097340415, 46.4928814870355], [9.310378097340415, 46.4928814870355]]]}}, {"type": "Feature", "properties": {"danger_level": 2}, "geometry": {"type": "Polygon", "coordinates": [[[9.83963751827219, 46.48444076252441], [9.83963751827219, 46.48444076252441]]]}}, {"type": "Feature", "properties": {"danger_level": 2}, "geometry": {"type": "Polygon", "coordinates": [[[10.035288304183004, 46.47528908595985], [10.035288304183004, 46.47528908595985]]]}}, {"type": "Feature", "properties": {"danger_level": 2}, "geometry": {"type": "Polygon", "coordinates": [[[9.458063408074805, 46.47306100926531], [9.458063408074805, 46.47306100926531]]]}}, {"type": "Feature", "properties": {"danger_level": 2}, "geometry": {"type": "Polygon", "coordinates": [[[8.392853597867232, 46.44190895355353], [8.392853597867232, 46.44190895355353]]]}}, {"type": "Feature", "properties": {"danger_level": 2}, "geometry": {"type": "Polygon", "coordinates": [[[9.461852293279929, 46.42123412787823], [9.461852293279929, 46.42123412787823]]]}}, {"type": "Feature", "properties": {"danger_level": 2}, "geometry": {"type": "Polygon", "coordinates": [[[10.118482225211997, 46.422750875819006], [10.118482225211997, 46.422750875819006]]]}}, {"type": "Feature", "properties": {"danger_level": 2}, "geometry": {"type": "Polygon", "coordinates": [[[10.08650524176105, 46.41563834168192], [10.08650524176105, 46.41563834168192]]]}}, {"type": "Feature", "properties": {"danger_level": 2}, "geometry": {"type": "Polygon", "coordinates": [[[10.149491847616645, 46.39657661458242], [10.149491847616645, 46.39657661458242]]]}}, {"type": "Feature", "properties": {"danger_level": 2}, "geometry": {"type": "Polygon", "coordinates": [[[9.269667938892136, 46.36746332459782], [9.269667938892136, 46.36746332459782]]]}}, {"type": "Feature", "properties": {"danger_level": 2}, "geometry": {"type": "Polygon", "coordinates": [[[9.915818017275054, 46.37277344919173], [9.915818017275054, 46.37277344919173]]]}}, {"type": "Feature", "properties": {"danger_level": 2}, "geometry": {"type": "Polygon", "coordinates": [[[8.4702164270378, 46.370925501233124], [8.4702164270378, 46.370925501233124]]]}}, {"type": "Feature", "properties": {"danger_level": 2}, "geometry": {"type": "Polygon", "coordinates": [[[9.846570381318232, 46.35859580283448], [9.846570381318232, 46.35859580283448]]]}}, {"type": "Feature", "properties": {"danger_level": 2}, "geometry": {"type": "Polygon", "coordinates": [[[9.988854538437, 46.33512421416191], [9.988854538437, 46.33512421416191]]]}}, {"type": "Feature", "properties": {"danger_level": 2}, "geometry": {"type": "Polygon", "coordinates": [[[8.795441266324143, 46.08315089338143], [8.875276240390816, 46.097233695904855], [8.91319180026089, 46.1264900050408], [8.982009497974913, 46.12587352012087], [9.035161157645561, 46.132796366590284], [9.071786902787233, 46.11767028189467], [9.092961579006932, 46.117480594227], [9.165662183696467, 46.159373525770526], [9.152589237900207, 46.16503987979176], [9.092948116216624, 46.20811835925823], [9.062798370297578, 46.26388088304919], [9.06408818502598, 46.30826327688076], [9.069919276884407, 46.326708519060325], [9.056953815648844, 46.33607340590086], [8.993322302429046, 46.332943936084575], [8.9404930964405, 46.33711668807306], [8.9195333893422, 46.34470344137932], [8.834834684463406, 46.34546219205001], [8.776389355737834, 46.33858676749751], [8.73890373411056, 46.32412458963874], [8.632492930208564, 46.30658036388062], [8.50512241920827, 46.296622891428754], [8.46255809764747, 46.289605201125504], [8.444191482796285, 46.295318977063665], [8.438467875498558, 46.28057226770339], [8.453703975299133, 46.25823880503686], [8.466024529170493, 46.22668272128054], [8.513237612422014, 46.211461792751095], [8.536575442646026, 46.19460499643812], [8.567370095929274, 46.16103366956295], [8.58811483390617, 46.14604985061809], [8.59805726465182, 46.12376380986847], [8.62150257943653, 46.1106055463748], [8.653157109205377, 46.106622482054], [8.674009331742976, 46.09533719592843], [8.695184007962675, 46.09514750826076], [8.7440093596247, 46.13540457202077], [8.781065043009173, 46.135072618602344], [8.77922434268696, 46.16283532570553], [8.829460456428396, 46.16053555108516], [8.847612102158184, 46.14742470950841], [8.847289648476083, 46.136329111050514], [8.812504603656622, 46.123692488642945], [8.772103436100135, 46.100007689694394], [8.795441266324143, 46.08315089338143]]]}}, {"type": "Feature", "properties": {"danger_level": 2}, "geometry": {"type": "Polygon", "coordinates": [[[9.998474515500547, 46.3017425749544], [9.998474515500547, 46.3017425749544]]]}}, {"type": "Feature", "properties": {"danger_level": 2}, "geometry": {"type": "Polygon", "coordinates": [[[9.998152061818447, 46.29064697649651], [9.998152061818447, 46.29064697649651]]]}}, {"type": "Feature", "properties": {"danger_level": 2}, "geometry": {"type": "Polygon", "coordinates": [[[9.632566443346539, 46.28282349030596], [9.632566443346539, 46.28282349030596]]]}}, {"type": "Feature", "properties": {"danger_level": 2}, "geometry": {"type": "Polygon", "coordinates": [[[10.054662668451416, 46.23094881030166], [10.054662668451416, 46.23094881030166]]]}}, {"type": "Feature", "properties": {"danger_level": 2}, "geometry": {"type": "Polygon", "coordinates": [[[10.075622375549715, 46.2233620569954], [10.075622375549715, 46.2233620569954]]]}}, {"type": "Feature", "properties": {"danger_level": 2}, "geometry": {"type": "Polygon", "coordinates": [[[8.15176333283733, 46.16290702363135], [8.15176333283733, 46.16290702363135]]]}}, {"type": "Feature", "properties": {"danger_level": 2}, "geometry": {"type": "Polygon", "coordinates": [[[7.605789953835796, 45.96062622127635], [7.605789953835796, 45.96062622127635]]]}}, {"type": "Feature", "properties": {"danger_level": 2}, "geometry": {"type": "Polygon", "coordinates": [[[7.626964630055495, 45.96043653360868], [7.626964630055495, 45.96043653360868]]]}}, {"type": "Feature", "properties": {"danger_level": 2}, "geometry": {"type": "Polygon", "coordinates": [[[7.747751657272463, 45.92605903414589], [7.747751657272463, 45.92605903414589]]]}}, {"type": "Feature", "properties": {"danger_level": 2}, "geometry": {"type": "Polygon", "coordinates": [[[7.721068342876438, 45.91889907809188], [7.721068342876438, 45.91889907809188]]]}}, {"type": "Feature", "properties": {"danger_level": 2}, "geometry": {"type": "Polygon", "coordinates": [[[7.805552078633834, 45.910743261782606], [7.805552078633834, 45.910743261782606]]]}}, {"type": "Feature", "properties": {"danger_level": 2}, "geometry": {"type": "Polygon", "coordinates": [[[7.302331064733883, 45.904152745431915], [7.302331064733883, 45.904152745431915]]]}}, {"type": "Feature", "properties": {"danger_level": 2}, "geometry": {"type": "Polygon", "coordinates": [[[7.3761199778207285, 45.89239324013717], [7.3761199778207285, 45.89239324013717]]]}}, {"type": "Feature", "properties": {"danger_level": 3}, "geometry": {"type": "Polygon", "coordinates": [[[7.3815211314363545, 45.89604435103955], [7.4029107767774525, 45.90325172901047], [7.489006780945351, 45.95057390499065], [7.51018145716505, 45.95038421732298], [7.55339068609005, 45.97959310454201], [7.611083622890721, 45.96057879935943], [7.648246790835894, 45.9639453787603], [7.710588489327289, 45.92269245474502], [7.742565472778238, 45.929804988882104], [7.784484886974836, 45.91463148226957], [7.842607762018307, 45.91041130836418], [7.8561106460573695, 45.91953908562013], [7.862371676158596, 45.95277845907688], [7.902987812836483, 45.983860323664025], [7.9665118414955804, 45.98329126066101], [7.996110701820817, 45.9996738378048], [8.018252739086817, 46.03277094551079], [8.01932758469382, 46.06975627370376], [8.043740260524832, 46.089884805583765], [8.086304582085631, 46.096902495887015], [8.137615541434068, 46.13158804945962], [8.148955271468816, 46.157382935360864], [8.149600178833017, 46.17957413227664], [8.124206679165395, 46.2167965700542], [8.087795903145123, 46.23931972038841], [8.082932172333, 46.25416127358251], [8.128841978065813, 46.28519571625274], [8.17129881506591, 46.288514873736695], [8.192688460407009, 46.295722251707616], [8.217208620798722, 46.31954931640691], [8.268519580147158, 46.35423486997952], [8.289801740927558, 46.35774371513114], [8.308813263142945, 46.374221136108766], [8.293792132463771, 46.403951664413896], [8.355690429922058, 46.438542374152654], [8.41424324320833, 46.44911633152445], [8.451298926592804, 46.448784378106026], [8.464264387828365, 46.43941949126549], [8.463511995903463, 46.41352976153041], [8.473561911209814, 46.39494225360009], [8.467515850229987, 46.36909994578193], [8.466118550940886, 46.32101901913107], [8.44959263641191, 46.29897008796604], [8.46255809764747, 46.289605201125504], [8.50512241920827, 46.296622891428754], [8.632492930208564, 46.30658036388062], [8.73890373411056, 46.32412458963874], [8.776389355737834, 46.33858676749751], [8.834834684463406, 46.34546219205001], [8.9195333893422, 46.34470344137932], [8.9404930964405, 46.33711668807306], [8.993322302429046, 46.332943936084575], [9.056953815648844, 46.33607340590086], [9.069919276884407, 46.326708519060325], [9.06408818502598, 46.30826327688076], [9.062798370297578, 46.26388088304919], [9.092948116216624, 46.20811835925823], [9.152589237900207, 46.16503987979176], [9.181865644543343, 46.17032685847766], [9.19860652819372, 46.19977285528128], [9.241923241679418, 46.232680275319616], [9.242460664482918, 46.2511729394161], [9.269896370803844, 46.28422262520518], [9.287282161818421, 46.33585981892459], [9.267074846645025, 46.36933630196593], [9.267934723130626, 46.39892456452031], [9.247297469714425, 46.41760691628446], [9.242433738902303, 46.432448469478565], [9.264253322486203, 46.45444997872668], [9.265005714411105, 46.480339708461756], [9.305191912846189, 46.49662744177171], [9.358236087956138, 46.49985175542182], [9.389138225800085, 46.46997896136594], [9.40501923296486, 46.469836695615186], [9.43764112378001, 46.499140426668056], [9.456007738631197, 46.493426650729894], [9.46087146944332, 46.47858509753579], [9.459581654714919, 46.43420270370423], [9.468341755292863, 46.37123280194235], [9.504752531313136, 46.34870965160814], [9.519773661992309, 46.31897912330301], [9.569364868369542, 46.29448815176686], [9.606205582632615, 46.28675913270985], [9.64326126601709, 46.28642717929142], [9.659357242303264, 46.293681979179254], [9.69101177207211, 46.28969891485845], [9.7098083251661, 46.29877927019748], [9.7106682016517, 46.328367532751855], [9.729679723867088, 46.34484495372948], [9.77710777624001, 46.337021090838626], [9.841384196824007, 46.36234175757069], [9.857265203988783, 46.362199491819936], [9.889457156561132, 46.37670909159562], [9.92111168632998, 46.372726027274815], [9.947687516165304, 46.376187450509526], [9.965946646455789, 46.36677514175207], [9.991662599805514, 46.34064830243239], [9.990910207880612, 46.314758572697315], [10.000745154065559, 46.2887739991284], [10.018896799795344, 46.27566315755165], [10.039963991454345, 46.271774937064684], [10.05811563718413, 46.25866409548793], [10.057363245259229, 46.23277436575285], [10.065142522000565, 46.22715543364853], [10.118079212549814, 46.22668121447935], [10.14767807287505, 46.24306379162314], [10.148860403042754, 46.283747652635405], [10.107370927088956, 46.313715290525124], [10.097750950025407, 46.347096929732636], [10.119785502730707, 46.376495504619335], [10.146791270808833, 46.39475105913123], [10.147221209051633, 46.40954519040842], [10.123775894266922, 46.42270345390209], [10.08650524176105, 46.41563834168192], [10.054958196552901, 46.42331993882202], [10.036806550823115, 46.43643078039877], [10.032695211935893, 46.47716206332796], [10.034092511224994, 46.525242989978814], [10.039923603083421, 46.54368823215838], [10.07265297845927, 46.57669049603055], [10.089393862109645, 46.606136492834175], [10.102896746148708, 46.61526427009012], [10.166528259368505, 46.6183937399064], [10.235775895325327, 46.63257138626366], [10.248633872000187, 46.61950796660383], [10.242587811020362, 46.59366565878567], [10.250259603201, 46.58434819386205], [10.281699163848447, 46.57296806390265], [10.312923755374495, 46.55419086830465], [10.344900738825443, 46.56130340244174], [10.413610951978765, 46.556988384702514], [10.450451666241838, 46.54925936564549], [10.470108095821427, 46.5879279835389], [10.465781787812805, 46.62126220082949], [10.442443957588793, 46.638118997142456], [10.39490842065517, 46.64224432721401], [10.376756774925385, 46.65535516879076], [10.367244282422535, 46.69243534081757], [10.383662712390812, 46.7107857391633], [10.384522588876413, 46.740374001717676], [10.422438148746489, 46.76963031085363], [10.407094564385213, 46.788265240700866], [10.407524502628014, 46.80305937197805], [10.43453027070614, 46.82131492648995], [10.44608496986229, 46.85450687802979], [10.441866146414368, 46.891539628139675], [10.452883422767018, 46.906238915583025], [10.459036968307544, 46.935779756220484], [10.446286476193382, 46.95254170869961], [10.40955324649101, 46.96396926057593], [10.37346492415284, 46.99758800936802], [10.35229024793314, 46.997777697035694], [10.322691387607904, 46.98139511989191], [10.300764319463301, 46.95569507782451], [10.300334381220502, 46.940900946547316], [10.281322859005114, 46.92442352556969], [10.239080991126416, 46.928501433724335], [10.219961984350329, 46.90832547992741], [10.216294046496216, 46.87321312910255], [10.130842949692518, 46.84808215003815], [10.088386112692419, 46.8447629925542], [10.051760367550747, 46.85988907724981], [10.005084707102727, 46.89360266987575], [9.957871623851206, 46.9088235984052], [9.926109609521657, 46.909108129906706], [9.866038549595272, 46.93739247809599], [9.855881149728225, 46.952281453207014], [9.867328364323674, 46.98177487192755], [9.86267960263295, 47.00401349076025], [9.844420472342465, 47.013425799517705], [9.812658458012917, 47.01371033101921], [9.76025919026717, 47.032677214284874], [9.712723653333548, 47.03680254435643], [9.655030716532876, 47.05581684953902], [9.61246639497208, 47.04879915923576], [9.589021080187369, 47.061957422729435], [9.610840663771267, 47.08395893197755], [9.612130478499669, 47.12834132580911], [9.607051778566145, 47.13578581336462], [9.552596841376788, 47.175118338094876], [9.542116987827637, 47.178911714748004], [9.467898136497992, 47.17587708876556], [9.452232098454617, 47.183416420154906], [9.36753339357582, 47.18417517082559], [9.325076556575722, 47.18085601334164], [9.266953681532252, 47.185076187247034], [9.113437278939434, 47.18645142283765], [9.108036125323808, 47.18280031193527], [8.938638715566217, 47.18431781327664], [8.902012970424545, 47.19944389797226], [8.848646341632497, 47.185123985864244], [8.694162577993376, 47.15321242608119], [8.651705740993279, 47.14989326859724], [8.603740265816855, 47.139224467391614], [8.555989759761832, 47.135952731824574], [8.518719107255958, 47.128887619604406], [8.499492615919172, 47.105013132988184], [8.530287269202418, 47.07144180611301], [8.511490716108431, 47.06236145077398], [8.477673032335273, 47.08301162374008], [8.483719093315097, 47.10885393155824], [8.460273778530388, 47.12201219505191], [8.444392771365612, 47.12215446080266], [8.425488733710925, 47.10937557264433], [8.424521372664623, 47.07608877727066], [8.411018488625562, 47.066961000014715], [8.204565395483497, 47.068810454774514], [8.173018350275347, 47.07649205191461], [8.098369560702901, 47.05866329465498], [8.034523078361705, 47.0481367592001], [7.932976005271833, 47.01575098024787], [7.890411683711034, 47.008733289944615], [7.729989343652789, 46.954677955162694], [7.69801236020184, 46.947565421025615], [7.628442270562918, 46.92229217621047], [7.54299117375922, 46.897161197146076], [7.5214940438574205, 46.886255286355855], [7.462726261449747, 46.868284263345465], [7.344868242952301, 46.8212466188668], [7.30997571357214, 46.80491146363993], [7.320348082560588, 46.797419554167504], [7.314516990702162, 46.77897431198794], [7.313012206852361, 46.727194852517776], [7.331056368021446, 46.71038547812173], [7.357309744174669, 46.70275130289855], [7.38064757439868, 46.685894506585576], [7.380110151595179, 46.66740184248909], [7.331499769054555, 46.63454184436768], [7.320052554459104, 46.60504842564714], [7.303634124490829, 46.58669802730141], [7.249515103773879, 46.546488385458325], [7.242609166308452, 46.49105781508579], [7.198325091776451, 46.424863599673785], [7.207192676915097, 46.365592230731195], [7.225451807205584, 46.35617992197374], [7.252350090723008, 46.370736943666344], [7.327106364856156, 46.39226423374527], [7.35368219469148, 46.395725656979984], [7.3897705170296515, 46.36210690818788], [7.4217475004806, 46.36921944232497], [7.485379013700397, 46.37234891214125], [7.565321472327769, 46.39013024748397], [7.602498103063251, 46.30285906185361], [7.514131460330341, 46.26850546169943], [7.503544122220491, 46.26860030553326], [7.423279209911018, 46.23972337173266], [7.402104533691319, 46.23991305940033], [7.40242698737342, 46.251008657858215], [7.375636188416696, 46.24015016898492], [7.377906826981707, 46.22718159315892], [7.3380430822287215, 46.221989458306865], [7.3270258058760716, 46.20729017086351], [7.316653436887623, 46.21478208033594], [7.295048822425123, 46.20017763672642], [7.257670685358549, 46.189413991686955], [7.1877781420375255, 46.153045148413916], [7.128902875069152, 46.131375592584234], [7.083100553897041, 46.10403968273331], [7.082778100214941, 46.092944084275416], [7.12739809121935, 46.07959613311407], [7.166401959486734, 46.05520000541176], [7.1970891282092815, 46.01793014571729], [7.243657304096602, 45.98051802027206], [7.2742369882584486, 45.93954962775828], [7.275970204019959, 45.908088387835804], [7.334093079063431, 45.90386821393041], [7.349759117106806, 45.896328882541056], [7.3815211314363545, 45.89604435103955]]]}}, {"type": "Feature", "properties": {"danger_level": 3}, "geometry": {"type": "Polygon", "coordinates": [[[9.482717760846072, 47.048111729790605], [9.472560360979024, 47.063000704901626], [9.496435614006534, 47.064636572685146], [9.482717760846072, 47.048111729790605]]]}}, {"type": "Feature", "properties": {"danger_level": 3}, "geometry": {"type": "Polygon", "coordinates": [[[7.032407576332189, 46.27282085613895], [7.032515060892889, 46.27651938895825], [6.8789986583000715, 46.27789462454887], [6.878891173739372, 46.27419609172957], [7.032407576332189, 46.27282085613895]]]}}, {"type": "Feature", "properties": {"danger_level": 4}, "geometry": {"type": "Polygon", "coordinates": [[[7.163298370016737, 45.857304788620915], [7.2009989607654115, 45.879164032118275], [7.23286845965566, 45.88257803343606], [7.262467319980897, 45.898960610579856], [7.278885749949172, 45.91731100892559], [7.2742369882584486, 45.93954962775828], [7.243657304096602, 45.98051802027206], [7.1970891282092815, 46.01793014571729], [7.166401959486734, 46.05520000541176], [7.12739809121935, 46.07959613311407], [7.082778100214941, 46.092944084275416], [7.083100553897041, 46.10403968273331], [7.128902875069152, 46.131375592584234], [7.1877781420375255, 46.153045148413916], [7.257670685358549, 46.189413991686955], [7.295048822425123, 46.20017763672642], [7.327455744118872, 46.2220843021407], [7.364511427503345, 46.22175234872227], [7.377906826981707, 46.22718159315892], [7.370342519361771, 46.240197590901836], [7.2644691382632764, 46.2411460292402], [7.24631749253349, 46.254256870816945], [7.2471773690190915, 46.28384513337132], [7.260787737618854, 46.29667144344657], [7.387835794937048, 46.29553331744054], [7.405987440666834, 46.28242247586378], [7.402104533691319, 46.23991305940033], [7.423279209911018, 46.23972337173266], [7.503544122220491, 46.26860030553326], [7.514131460330341, 46.26850546169943], [7.602498103063251, 46.30285906185361], [7.565321472327769, 46.39013024748397], [7.485379013700397, 46.37234891214125], [7.4217475004806, 46.36921944232497], [7.3897705170296515, 46.36210690818788], [7.35368219469148, 46.395725656979984], [7.327106364856156, 46.39226423374527], [7.289620743228881, 46.37780205588651], [7.252350090723008, 46.370736943666344], [7.225451807205584, 46.35617992197374], [7.207192676915097, 46.365592230731195], [7.198325091776451, 46.424863599673785], [7.242609166308452, 46.49105781508579], [7.255023741950204, 46.55383802918], [7.303634124490829, 46.58669802730141], [7.320052554459104, 46.60504842564714], [7.331499769054555, 46.63454184436768], [7.380110151595179, 46.66740184248909], [7.38064757439868, 46.685894506585576], [7.357309744174669, 46.70275130289855], [7.331056368021446, 46.71038547812173], [7.313012206852361, 46.727194852517776], [7.314516990702162, 46.77897431198794], [7.320348082560588, 46.797419554167504], [7.3019814677094015, 46.80313333010566], [7.183586026408454, 46.737603021530504], [7.107969875789705, 46.6864874688972], [7.102676206734781, 46.686534890814116], [7.032461209731657, 46.63907044908319], [6.986658888559545, 46.611734539232266], [6.94863584412877, 46.57877969727702], [6.921307622368545, 46.54942854430723], [6.90467422327887, 46.52368108032291], [6.87205233246372, 46.49437734927004], [6.850017779758419, 46.46497877438333], [6.86276827187258, 46.448216821904204], [6.899501501574953, 46.43678927002789], [6.922839331798964, 46.41993247371492], [6.927595578050387, 46.40139238770152], [6.914092694011326, 46.39226461044557], [6.877037010626853, 46.392596563864], [6.823885350956204, 46.38567371739458], [6.783376698839017, 46.35829038562673], [6.782946760596217, 46.343496254349546], [6.8423729131584, 46.29302070924449], [6.873704989245147, 46.27794204646579], [7.032515060892889, 46.27651938895825], [7.050666706622676, 46.263408547381495], [7.040563157916859, 45.915746462367586], [7.076221542012229, 45.8673335822983], [7.099774341357641, 45.85787385162393], [7.12127147125944, 45.86877976241415], [7.142446147479139, 45.86859007474648], [7.163298370016737, 45.857304788620915]]]}}]}