{"type": "FeatureCollection", "features": [{"type": "Feature", "properties": {"date": "23.03.2002", "danger_level": 2, "url": "https://www.slf.ch/fileadmin/user_upload/import/lwdarchiv/public/2002/nbk/de/gif/20020323_nbk_de_c.gif"}, "geometry": {"type": "Polygon", "coordinates": [[[9.652427619361482, 47.387381580286274], [9.652427619361482, 47.387381580286274]]]}}, {"type": "Feature", "properties": {"date": "23.03.2002", "danger_level": 2, "url": "https://www.slf.ch/fileadmin/user_upload/import/lwdarchiv/public/2002/nbk/de/gif/20020323_nbk_de_c.gif"}, "geometry": {"type": "Polygon", "coordinates": [[[9.641333966378637, 47.379782609986634], [9.641333966378637, 47.379782609986634]]]}}, {"type": "Feature", "properties": {"date": "23.03.2002", "danger_level": 2, "url": "https://www.slf.ch/fileadmin/user_upload/import/lwdarchiv/public/2002/nbk/de/gif/20020323_nbk_de_c.gif"}, "geometry": {"type": "Polygon", "coordinates": [[[9.539707911676215, 47.254351134441094], [9.539707911676215, 47.254351134441094]]]}}, {"type": "Feature", "properties": {"date": "23.03.2002", "danger_level": 2, "url": "https://www.slf.ch/fileadmin/user_upload/import/lwdarchiv/public/2002/nbk/de/gif/20020323_nbk_de_c.gif"}, "geometry": {"type": "Polygon", "coordinates": [[[9.550088293516332, 47.239133807601206], [9.550088293516332, 47.239133807601206]]]}}, {"type": "Feature", "properties": {"date": "23.03.2002", "danger_level": 2, "url": "https://www.slf.ch/fileadmin/user_upload/import/lwdarchiv/public/2002/nbk/de/gif/20020323_nbk_de_c.gif"}, "geometry": {"type": "Polygon", "coordinates": [[[9.19913326787409, 47.12525910847012], [9.19913326787409, 47.12525910847012]]]}}, {"type": "Feature", "properties": {"date": "23.03.2002", "danger_level": 2, "url": "https://www.slf.ch/fileadmin/user_upload/import/lwdarchiv/public/2002/nbk/de/gif/20020323_nbk_de_c.gif"}, "geometry": {"type": "Polygon", "coordinates": [[[9.18780185784367, 47.11005470579064], [9.18780185784367, 47.11005470579064]]]}}, {"type": "Feature", "properties": {"date": "23.03.2002", "danger_level": 2, "url": "https://www.slf.ch/fileadmin/user_upload/import/lwdarchiv/public/2002/nbk/de/gif/20020323_nbk_de_c.gif"}, "geometry": {"type": "Polygon", "coordinates": [[[8.317665883689136, 47.05733364554805], [8.317665883689136, 47.05733364554805]]]}}, {"type": "Feature", "properties": {"date": "23.03.2002", "danger_level": 2, "url": "https://www.slf.ch/fileadmin/user_upload/import/lwdarchiv/public/2002/nbk/de/gif/20020323_nbk_de_c.gif"}, "geometry": {"type": "Polygon", "coordinates": [[[8.300668768643504, 47.034527041528825], [8.300668768643504, 47.034527041528825]]]}}, {"type": "Feature", "properties": {"date": "23.03.2002", "danger_level": 2, "url": "https://www.slf.ch/fileadmin/user_upload/import/lwdarchiv/public/2002/nbk/de/gif/20020323_nbk_de_c.gif"}, "geometry": {"type": "Polygon", "coordinates": [[[10.378740690580964, 47.00667053984039], [10.378740690580964, 47.00667053984039]]]}}, {"type": "Feature", "properties": {"date": "23.03.2002", "danger_level": 2, "url": "https://www.slf.ch/fileadmin/user_upload/import/lwdarchiv/public/2002/nbk/de/gif/20020323_nbk_de_c.gif"}, "geometry": {"type": "Polygon", "coordinates": [[[8.586685711595097, 46.98111776974455], [8.586685711595097, 46.98111776974455]]]}}, {"type": "Feature", "properties": {"date": "23.03.2002", "danger_level": 2, "url": "https://www.slf.ch/fileadmin/user_upload/import/lwdarchiv/public/2002/nbk/de/gif/20020323_nbk_de_c.gif"}, "geometry": {"type": "Polygon", "coordinates": [[[10.46356692315872, 46.94197266797011], [10.46356692315872, 46.94197266797011]]]}}, {"type": "Feature", "properties": {"date": "23.03.2002", "danger_level": 2, "url": "https://www.slf.ch/fileadmin/user_upload/import/lwdarchiv/public/2002/nbk/de/gif/20020323_nbk_de_c.gif"}, "geometry": {"type": "Polygon", "coordinates": [[[10.257186021864824, 46.93829273130406], [10.257186021864824, 46.93829273130406]]]}}, {"type": "Feature", "properties": {"date": "23.03.2002", "danger_level": 2, "url": "https://www.slf.ch/fileadmin/user_upload/import/lwdarchiv/public/2002/nbk/de/gif/20020323_nbk_de_c.gif"}, "geometry": {"type": "Polygon", "coordinates": [[[10.284206883179209, 46.93447385991363], [10.284206883179209, 46.93447385991363]]]}}, {"type": "Feature", "properties": {"date": "23.03.2002", "danger_level": 2, "url": "https://www.slf.ch/fileadmin/user_upload/import/lwdarchiv/public/2002/nbk/de/gif/20020323_nbk_de_c.gif"}, "geometry": {"type": "Polygon", "coordinates": [[[10.229333010883925, 46.91549258936505], [10.229333010883925, 46.91549258936505]]]}}, {"type": "Feature", "properties": {"date": "23.03.2002", "danger_level": 2, "url": "https://www.slf.ch/fileadmin/user_upload/import/lwdarchiv/public/2002/nbk/de/gif/20020323_nbk_de_c.gif"}, "geometry": {"type": "Polygon", "coordinates": [[[9.593312070480396, 46.88544889153759], [9.593312070480396, 46.88544889153759]]]}}, {"type": "Feature", "properties": {"date": "23.03.2002", "danger_level": 2, "url": "https://www.slf.ch/fileadmin/user_upload/import/lwdarchiv/public/2002/nbk/de/gif/20020323_nbk_de_c.gif"}, "geometry": {"type": "Polygon", "coordinates": [[[9.527938937821206, 46.87788223163898], [9.582456174545127, 46.8854553536178], [9.517320798933515, 46.88549412609902], [9.527938937821206, 46.87788223163898]]]}}, {"type": "Feature", "properties": {"date": "23.03.2002", "danger_level": 2, "url": "https://www.slf.ch/fileadmin/user_upload/import/lwdarchiv/public/2002/nbk/de/gif/20020323_nbk_de_c.gif"}, "geometry": {"type": "Polygon", "coordinates": [[[9.51636977074321, 46.85507239657966], [9.51636977074321, 46.85507239657966]]]}}, {"type": "Feature", "properties": {"date": "23.03.2002", "danger_level": 2, "url": "https://www.slf.ch/fileadmin/user_upload/import/lwdarchiv/public/2002/nbk/de/gif/20020323_nbk_de_c.gif"}, "geometry": {"type": "Polygon", "coordinates": [[[9.532772493169901, 46.85886541964928], [9.532772493169901, 46.85886541964928]]]}}, {"type": "Feature", "properties": {"date": "23.03.2002", "danger_level": 2, "url": "https://www.slf.ch/fileadmin/user_upload/import/lwdarchiv/public/2002/nbk/de/gif/20020323_nbk_de_c.gif"}, "geometry": {"type": "Polygon", "coordinates": [[[9.527106788154692, 46.85126321830954], [9.527106788154692, 46.85126321830954]]]}}, {"type": "Feature", "properties": {"date": "23.03.2002", "danger_level": 2, "url": "https://www.slf.ch/fileadmin/user_upload/import/lwdarchiv/public/2002/nbk/de/gif/20020323_nbk_de_c.gif"}, "geometry": {"type": "Polygon", "coordinates": [[[10.113325168659207, 46.850914265978545], [10.113325168659207, 46.850914265978545]]]}}, {"type": "Feature", "properties": {"date": "23.03.2002", "danger_level": 2, "url": "https://www.slf.ch/fileadmin/user_upload/import/lwdarchiv/public/2002/nbk/de/gif/20020323_nbk_de_c.gif"}, "geometry": {"type": "Polygon", "coordinates": [[[10.425768580306242, 46.77467254185423], [10.425768580306242, 46.77467254185423]]]}}, {"type": "Feature", "properties": {"date": "23.03.2002", "danger_level": 2, "url": "https://www.slf.ch/fileadmin/user_upload/import/lwdarchiv/public/2002/nbk/de/gif/20020323_nbk_de_c.gif"}, "geometry": {"type": "Polygon", "coordinates": [[[10.374182842550411, 46.68723914884698], [10.374182842550411, 46.68723914884698]]]}}, {"type": "Feature", "properties": {"date": "23.03.2002", "danger_level": 2, "url": "https://www.slf.ch/fileadmin/user_upload/import/lwdarchiv/public/2002/nbk/de/gif/20020323_nbk_de_c.gif"}, "geometry": {"type": "Polygon", "coordinates": [[[10.176874659334965, 46.62651200725192], [10.176874659334965, 46.62651200725192]]]}}, {"type": "Feature", "properties": {"date": "23.03.2002", "danger_level": 2, "url": "https://www.slf.ch/fileadmin/user_upload/import/lwdarchiv/public/2002/nbk/de/gif/20020323_nbk_de_c.gif"}, "geometry": {"type": "Polygon", "coordinates": [[[10.14418809300537, 46.62272867730261], [10.14418809300537, 46.62272867730261]]]}}, {"type": "Feature", "properties": {"date": "23.03.2002", "danger_level": 2, "url": "https://www.slf.ch/fileadmin/user_upload/import/lwdarchiv/public/2002/nbk/de/gif/20020323_nbk_de_c.gif"}, "geometry": {"type": "Polygon", "coordinates": [[[10.252509295310483, 46.61505862412073], [10.252509295310483, 46.61505862412073]]]}}, {"type": "Feature", "properties": {"date": "23.03.2002", "danger_level": 2, "url": "https://www.slf.ch/fileadmin/user_upload/import/lwdarchiv/public/2002/nbk/de/gif/20020323_nbk_de_c.gif"}, "geometry": {"type": "Polygon", "coordinates": [[[8.591557217214357, 46.61604732239188], [8.591557217214357, 46.61604732239188]]]}}, {"type": "Feature", "properties": {"date": "23.03.2002", "danger_level": 2, "url": "https://www.slf.ch/fileadmin/user_upload/import/lwdarchiv/public/2002/nbk/de/gif/20020323_nbk_de_c.gif"}, "geometry": {"type": "Polygon", "coordinates": [[[10.11692947464341, 46.61894211631319], [10.11692947464341, 46.61894211631319]]]}}, {"type": "Feature", "properties": {"date": "23.03.2002", "danger_level": 2, "url": "https://www.slf.ch/fileadmin/user_upload/import/lwdarchiv/public/2002/nbk/de/gif/20020323_nbk_de_c.gif"}, "geometry": {"type": "Polygon", "coordinates": [[[10.094623290153933, 46.599941459524], [10.094623290153933, 46.599941459524]]]}}, {"type": "Feature", "properties": {"date": "23.03.2002", "danger_level": 2, "url": "https://www.slf.ch/fileadmin/user_upload/import/lwdarchiv/public/2002/nbk/de/gif/20020323_nbk_de_c.gif"}, "geometry": {"type": "Polygon", "coordinates": [[[10.474341890840766, 46.59210985433703], [10.474341890840766, 46.59210985433703]]]}}, {"type": "Feature", "properties": {"date": "23.03.2002", "danger_level": 2, "url": "https://www.slf.ch/fileadmin/user_upload/import/lwdarchiv/public/2002/nbk/de/gif/20020323_nbk_de_c.gif"}, "geometry": {"type": "Polygon", "coordinates": [[[9.762805192985507, 46.57732225583069], [9.762805192985507, 46.57732225583069]]]}}, {"type": "Feature", "properties": {"date": "23.03.2002", "danger_level": 2, "url": "https://www.slf.ch/fileadmin/user_upload/import/lwdarchiv/public/2002/nbk/de/gif/20020323_nbk_de_c.gif"}, "geometry": {"type": "Polygon", "coordinates": [[[10.451441313732348, 46.55409561659824], [10.451441313732348, 46.55409561659824]]]}}, {"type": "Feature", "properties": {"date": "23.03.2002", "danger_level": 2, "url": "https://www.slf.ch/fileadmin/user_upload/import/lwdarchiv/public/2002/nbk/de/gif/20020323_nbk_de_c.gif"}, "geometry": {"type": "Polygon", "coordinates": [[[10.043394187969465, 46.523916215086516], [10.043394187969465, 46.523916215086516]]]}}, {"type": "Feature", "properties": {"date": "23.03.2002", "danger_level": 2, "url": "https://www.slf.ch/fileadmin/user_upload/import/lwdarchiv/public/2002/nbk/de/gif/20020323_nbk_de_c.gif"}, "geometry": {"type": "Polygon", "coordinates": [[[9.841371327929112, 46.486008601671074], [9.841371327929112, 46.486008601671074]]]}}, {"type": "Feature", "properties": {"date": "23.03.2002", "danger_level": 2, "url": "https://www.slf.ch/fileadmin/user_upload/import/lwdarchiv/public/2002/nbk/de/gif/20020323_nbk_de_c.gif"}, "geometry": {"type": "Polygon", "coordinates": [[[9.32595402805142, 46.49392098286059], [9.32595402805142, 46.49392098286059]]]}}, {"type": "Feature", "properties": {"date": "23.03.2002", "danger_level": 2, "url": "https://www.slf.ch/fileadmin/user_upload/import/lwdarchiv/public/2002/nbk/de/gif/20020323_nbk_de_c.gif"}, "geometry": {"type": "Polygon", "coordinates": [[[9.46093945609955, 46.47102390971852], [9.46093945609955, 46.47102390971852]]]}}, {"type": "Feature", "properties": {"date": "23.03.2002", "danger_level": 2, "url": "https://www.slf.ch/fileadmin/user_upload/import/lwdarchiv/public/2002/nbk/de/gif/20020323_nbk_de_c.gif"}, "geometry": {"type": "Polygon", "coordinates": [[[9.016636894437388, 45.801997881420476], [9.030503960665945, 45.81149659429502], [9.047976589806726, 45.84951406307392], [9.070282774296203, 45.868514719863114], [9.070758288391355, 45.883725584622795], [9.046867475894048, 45.900852347157894], [9.025274562547297, 45.90466798750822], [9.006692819493836, 45.917988802813305], [9.0070494550652, 45.92939695138306], [8.988824347583101, 45.9541259152579], [8.958554558927855, 45.94083417931374], [8.963150357228972, 45.91421193494419], [8.949283291000416, 45.904713222069645], [8.930463790899378, 45.91042860499489], [8.947579784468797, 45.93703792520402], [8.948649691182888, 45.9712623709133], [8.962516757411445, 45.980761083787854], [8.98941874020204, 45.9731394962075], [9.008832632922019, 45.98643769423187], [9.004474591668474, 46.02066537098125], [9.029435310879876, 46.037763054155434], [9.056812807765624, 46.04535233133477], [9.076226700485602, 46.058650529359134], [9.072106416279636, 46.100483638488356], [9.107923031426305, 46.117574859582334], [9.16339129634053, 46.155569711080524], [9.18823313702814, 46.168864678064786], [9.194255477614716, 46.187875027974286], [9.244414673085092, 46.2296758267025], [9.250674770719241, 46.25629160899183], [9.284550122286717, 46.298102100840346], [9.290929098444655, 46.32852059931961], [9.270406091811997, 46.36656068537922], [9.271357120002301, 46.39698241489858], [9.252062105806111, 46.38748693306414], [9.170167372196444, 46.37232453390598], [9.099604048617195, 46.372366537427304], [9.061727291367543, 46.37619187089794], [8.975474516504331, 46.39525714848917], [8.93807327334983, 46.41429334671949], [8.874245561499887, 46.45616199728983], [8.820441595918691, 46.47140517245053], [8.771590064209983, 46.471434251811445], [8.70597917450322, 46.45626215953299], [8.651699694826876, 46.45629446993401], [8.602610406070589, 46.44871811691508], [8.558711308234361, 46.43353310047622], [8.519883522794405, 46.40693670442749], [8.486840320893448, 46.391745225908416], [8.46802082079241, 46.397460608833654], [8.465405493269074, 46.313800852655405], [8.437314725240599, 46.28339527833655], [8.43672033262166, 46.264381697386945], [8.452409783905622, 46.24535842331704], [8.45193426981047, 46.23014755855736], [8.481134151751625, 46.209214848792236], [8.513464082509856, 46.201590030171786], [8.537354895007166, 46.18446326763669], [8.563543606655033, 46.154025382916814], [8.613979766371575, 46.117868884231605], [8.717110777756629, 46.117807494469666], [8.750035101133797, 46.12919625679882], [8.785495080709104, 46.134879329323034], [8.788862886573755, 46.15579265284755], [8.832167591791043, 46.15196408833681], [8.850749334844505, 46.13864327303174], [8.831216563600739, 46.12154235881745], [8.798292240223567, 46.1101535964883], [8.77321264248838, 46.0892531971242], [8.786485316097995, 46.07973832904914], [8.824243194823861, 46.07211027938859], [8.84813400732117, 46.05498351685349], [8.853086441193652, 46.039769421053705], [8.791476957169067, 45.9789615034561], [8.804630752254894, 45.96564391919112], [8.826342544125433, 45.965630995030715], [8.858315839312299, 45.9465980278405], [8.89330030479245, 45.93707023560504], [8.8928247906973, 45.92185937084536], [8.919370137916532, 45.90282963469525], [8.918656866773805, 45.880013337555724], [8.93422743953398, 45.8571873472959], [8.930384119574178, 45.82106315901171], [8.973688824791466, 45.817234594500974], [9.016636894437388, 45.801997881420476]]]}}, {"type": "Feature", "properties": {"date": "23.03.2002", "danger_level": 2, "url": "https://www.slf.ch/fileadmin/user_upload/import/lwdarchiv/public/2002/nbk/de/gif/20020323_nbk_de_c.gif"}, "geometry": {"type": "Polygon", "coordinates": [[[10.04137325306507, 46.45927003985787], [10.04137325306507, 46.45927003985787]]]}}, {"type": "Feature", "properties": {"date": "23.03.2002", "danger_level": 2, "url": "https://www.slf.ch/fileadmin/user_upload/import/lwdarchiv/public/2002/nbk/de/gif/20020323_nbk_de_c.gif"}, "geometry": {"type": "Polygon", "coordinates": [[[9.464703104734154, 46.41778265201953], [9.464703104734154, 46.41778265201953]]]}}, {"type": "Feature", "properties": {"date": "23.03.2002", "danger_level": 2, "url": "https://www.slf.ch/fileadmin/user_upload/import/lwdarchiv/public/2002/nbk/de/gif/20020323_nbk_de_c.gif"}, "geometry": {"type": "Polygon", "coordinates": [[[9.63966463933351, 46.28458096104896], [9.672588962710682, 46.295969723378114], [9.7050377719927, 46.29214762094758], [9.719023716745044, 46.305449050012044], [9.714427918443926, 46.332071294381585], [9.742280929424824, 46.3548714363206], [9.732138304632283, 46.37769419554033], [9.708247492134975, 46.39482095807543], [9.643825387666089, 46.417676027696174], [9.611138821336496, 46.41389269774686], [9.578095619435537, 46.39870121922779], [9.539148955471793, 46.36830210698914], [9.51719940655368, 46.36070959876971], [9.490059666715508, 46.36072575397022], [9.503332340325123, 46.35121088589516], [9.52397422548157, 46.31697351602547], [9.542555968535034, 46.3036527007204], [9.596359934116226, 46.28840952555969], [9.63966463933351, 46.28458096104896]]]}}, {"type": "Feature", "properties": {"date": "23.03.2002", "danger_level": 2, "url": "https://www.slf.ch/fileadmin/user_upload/import/lwdarchiv/public/2002/nbk/de/gif/20020323_nbk_de_c.gif"}, "geometry": {"type": "Polygon", "coordinates": [[[9.464227590639002, 46.402571787259845], [9.464227590639002, 46.402571787259845]]]}}, {"type": "Feature", "properties": {"date": "23.03.2002", "danger_level": 2, "url": "https://www.slf.ch/fileadmin/user_upload/import/lwdarchiv/public/2002/nbk/de/gif/20020323_nbk_de_c.gif"}, "geometry": {"type": "Polygon", "coordinates": [[[10.040976153367094, 46.27293371551166], [10.060390046087072, 46.28623191353603], [10.063837523276923, 46.396510683043715], [10.011261550132197, 46.36421829031036], [9.981229518524525, 46.358531986746044], [9.991847657412219, 46.350920092286], [9.990896629221915, 46.320498362766635], [10.00092037549067, 46.29387288735699], [10.040976153367094, 46.27293371551166]]]}}, {"type": "Feature", "properties": {"date": "23.03.2002", "danger_level": 2, "url": "https://www.slf.ch/fileadmin/user_upload/import/lwdarchiv/public/2002/nbk/de/gif/20020323_nbk_de_c.gif"}, "geometry": {"type": "Polygon", "coordinates": [[[8.301339061803574, 46.36143335175252], [8.301339061803574, 46.36143335175252]]]}}, {"type": "Feature", "properties": {"date": "23.03.2002", "danger_level": 2, "url": "https://www.slf.ch/fileadmin/user_upload/import/lwdarchiv/public/2002/nbk/de/gif/20020323_nbk_de_c.gif"}, "geometry": {"type": "Polygon", "coordinates": [[[6.77477801913664, 46.320511395932], [6.77477801913664, 46.320511395932]]]}}, {"type": "Feature", "properties": {"date": "23.03.2002", "danger_level": 2, "url": "https://www.slf.ch/fileadmin/user_upload/import/lwdarchiv/public/2002/nbk/de/gif/20020323_nbk_de_c.gif"}, "geometry": {"type": "Polygon", "coordinates": [[[8.141194364695053, 46.2740645795473], [8.141194364695053, 46.2740645795473]]]}}, {"type": "Feature", "properties": {"date": "23.03.2002", "danger_level": 2, "url": "https://www.slf.ch/fileadmin/user_upload/import/lwdarchiv/public/2002/nbk/de/gif/20020323_nbk_de_c.gif"}, "geometry": {"type": "Polygon", "coordinates": [[[6.853938546699185, 46.24821132272199], [6.853938546699185, 46.24821132272199]]]}}, {"type": "Feature", "properties": {"date": "23.03.2002", "danger_level": 2, "url": "https://www.slf.ch/fileadmin/user_upload/import/lwdarchiv/public/2002/nbk/de/gif/20020323_nbk_de_c.gif"}, "geometry": {"type": "Polygon", "coordinates": [[[8.026097086534028, 46.06497980990372], [8.06456823640262, 46.080168057382686], [8.0839821291226, 46.093466255407044], [8.090004469709173, 46.11247660531655], [8.120036501316845, 46.11816290888087], [8.139450394036823, 46.131461106905235], [8.15090068259103, 46.15046822577463], [8.135805623926007, 46.188505080794144], [8.101534429588582, 46.22084917016913], [8.082833808011332, 46.23036726928429], [8.080535908860771, 46.243678391469054], [8.04206475899218, 46.228490143990086], [7.9687280221672205, 46.2266324049365], [7.962705681580647, 46.207622055026995], [7.983228688213304, 46.16958196896739], [7.982634295594364, 46.15056838801779], [7.992539163339329, 46.12014019641822], [8.026097086534028, 46.06497980990372]]]}}, {"type": "Feature", "properties": {"date": "23.03.2002", "danger_level": 2, "url": "https://www.slf.ch/fileadmin/user_upload/import/lwdarchiv/public/2002/nbk/de/gif/20020323_nbk_de_c.gif"}, "geometry": {"type": "Polygon", "coordinates": [[[7.384807540813265, 46.21367023508273], [7.384807540813265, 46.21367023508273]]]}}, {"type": "Feature", "properties": {"date": "23.03.2002", "danger_level": 2, "url": "https://www.slf.ch/fileadmin/user_upload/import/lwdarchiv/public/2002/nbk/de/gif/20020323_nbk_de_c.gif"}, "geometry": {"type": "Polygon", "coordinates": [[[7.335242737961828, 46.190883017304124], [7.335242737961828, 46.190883017304124]]]}}, {"type": "Feature", "properties": {"date": "23.03.2002", "danger_level": 2, "url": "https://www.slf.ch/fileadmin/user_upload/import/lwdarchiv/public/2002/nbk/de/gif/20020323_nbk_de_c.gif"}, "geometry": {"type": "Polygon", "coordinates": [[[7.307984119599867, 46.187096456314706], [7.307984119599867, 46.187096456314706]]]}}, {"type": "Feature", "properties": {"date": "23.03.2002", "danger_level": 2, "url": "https://www.slf.ch/fileadmin/user_upload/import/lwdarchiv/public/2002/nbk/de/gif/20020323_nbk_de_c.gif"}, "geometry": {"type": "Polygon", "coordinates": [[[7.324149084978983, 46.18328404700448], [7.324149084978983, 46.18328404700448]]]}}, {"type": "Feature", "properties": {"date": "23.03.2002", "danger_level": 2, "url": "https://www.slf.ch/fileadmin/user_upload/import/lwdarchiv/public/2002/nbk/de/gif/20020323_nbk_de_c.gif"}, "geometry": {"type": "Polygon", "coordinates": [[[6.7968059824519305, 46.15697844456492], [6.7968059824519305, 46.15697844456492]]]}}, {"type": "Feature", "properties": {"date": "23.03.2002", "danger_level": 2, "url": "https://www.slf.ch/fileadmin/user_upload/import/lwdarchiv/public/2002/nbk/de/gif/20020323_nbk_de_c.gif"}, "geometry": {"type": "Polygon", "coordinates": [[[6.8753721173955356, 46.0656647904053], [6.8753721173955356, 46.0656647904053]]]}}, {"type": "Feature", "properties": {"date": "23.03.2002", "danger_level": 2, "url": "https://www.slf.ch/fileadmin/user_upload/import/lwdarchiv/public/2002/nbk/de/gif/20020323_nbk_de_c.gif"}, "geometry": {"type": "Polygon", "coordinates": [[[8.014171283884666, 46.030761826274635], [8.014171283884666, 46.030761826274635]]]}}, {"type": "Feature", "properties": {"date": "23.03.2002", "danger_level": 2, "url": "https://www.slf.ch/fileadmin/user_upload/import/lwdarchiv/public/2002/nbk/de/gif/20020323_nbk_de_c.gif"}, "geometry": {"type": "Polygon", "coordinates": [[[6.8849203495691365, 46.023828450235975], [6.8849203495691365, 46.023828450235975]]]}}, {"type": "Feature", "properties": {"date": "23.03.2002", "danger_level": 2, "url": "https://www.slf.ch/fileadmin/user_upload/import/lwdarchiv/public/2002/nbk/de/gif/20020323_nbk_de_c.gif"}, "geometry": {"type": "Polygon", "coordinates": [[[7.001957634381334, 45.94770304355532], [7.001957634381334, 45.94770304355532]]]}}, {"type": "Feature", "properties": {"date": "23.03.2002", "danger_level": 2, "url": "https://www.slf.ch/fileadmin/user_upload/import/lwdarchiv/public/2002/nbk/de/gif/20020323_nbk_de_c.gif"}, "geometry": {"type": "Polygon", "coordinates": [[[7.852837801538268, 45.90536589217022], [7.852837801538268, 45.90536589217022]]]}}, {"type": "Feature", "properties": {"date": "23.03.2002", "danger_level": 2, "url": "https://www.slf.ch/fileadmin/user_upload/import/lwdarchiv/public/2002/nbk/de/gif/20020323_nbk_de_c.gif"}, "geometry": {"type": "Polygon", "coordinates": [[[7.71702022382362, 45.90164395198284], [7.71702022382362, 45.90164395198284]]]}}, {"type": "Feature", "properties": {"date": "23.03.2002", "danger_level": 2, "url": "https://www.slf.ch/fileadmin/user_upload/import/lwdarchiv/public/2002/nbk/de/gif/20020323_nbk_de_c.gif"}, "geometry": {"type": "Polygon", "coordinates": [[[7.819913478161097, 45.89397712984107], [7.819913478161097, 45.89397712984107]]]}}, {"type": "Feature", "properties": {"date": "23.03.2002", "danger_level": 2, "url": "https://www.slf.ch/fileadmin/user_upload/import/lwdarchiv/public/2002/nbk/de/gif/20020323_nbk_de_c.gif"}, "geometry": {"type": "Polygon", "coordinates": [[[7.298473837696831, 45.882879161121075], [7.298473837696831, 45.882879161121075]]]}}, {"type": "Feature", "properties": {"date": "23.03.2002", "danger_level": 3, "url": "https://www.slf.ch/fileadmin/user_upload/import/lwdarchiv/public/2002/nbk/de/gif/20020323_nbk_de_c.gif"}, "geometry": {"type": "Polygon", "coordinates": [[[7.16677654418815, 45.83732411180448], [7.2000575031366845, 45.86012102270339], [7.2271972429748566, 45.86010486750288], [7.266025028414813, 45.886701263551615], [7.325613577535003, 45.88286300592057], [7.36325257773708, 45.8714322400701], [7.3961769011142495, 45.88282100239925], [7.45984652724182, 45.92271236543224], [7.520029468980949, 45.9378876887508], [7.545109066716138, 45.95878808811491], [7.588057136362062, 45.94355137503441], [7.64776456400604, 45.94351583359329], [7.6984384807701565, 45.91496476728792], [7.706283206412138, 45.905453130252965], [7.749825668677001, 45.90922999812207], [7.771180824976176, 45.8978089253919], [7.820032356684885, 45.897779846030986], [7.850064388292556, 45.90346614959531], [7.8621090694657045, 45.941486849414304], [7.9037102681513725, 45.96998298803795], [7.963417695795352, 45.96994744659683], [7.993806362974387, 45.98704189873091], [8.016706940082804, 46.02505613646971], [8.012111141781684, 46.05167838083925], [8.023442551812105, 46.06688278351873], [8.018490117939622, 46.08209687931851], [7.992539163339329, 46.12014019641822], [7.982634295594364, 46.15056838801779], [7.983228688213304, 46.16958196896739], [7.962705681580647, 46.207622055026995], [7.9687280221672205, 46.2266324049365], [8.04206475899218, 46.228490143990086], [8.063895429386504, 46.232279936019594], [8.12491052079215, 46.274074272667605], [8.173880931024648, 46.27784790949661], [8.204269598203684, 46.29494236163069], [8.273723807870251, 46.34623864219334], [8.298446770034074, 46.35573089298768], [8.288779659336685, 46.393764516967096], [8.368733129367158, 46.433646186879784], [8.417822418123444, 46.4412225398987], [8.45039010592925, 46.441203153658094], [8.463662779538867, 46.431688285583036], [8.46283062987235, 46.40506927225359], [8.481412372925814, 46.39174845694852], [8.519883522794405, 46.40693670442749], [8.558711308234361, 46.43353310047622], [8.602610406070589, 46.44871811691508], [8.651699694826876, 46.45629446993401], [8.70597917450322, 46.45626215953299], [8.771590064209983, 46.471434251811445], [8.820441595918691, 46.47140517245053], [8.874245561499887, 46.45616199728983], [8.93807327334983, 46.41429334671949], [8.975474516504331, 46.39525714848917], [9.061727291367543, 46.37619187089794], [9.099604048617195, 46.372366537427304], [9.170167372196444, 46.37232453390598], [9.252062105806111, 46.38748693306414], [9.266048050558453, 46.40078836212861], [9.244930651306856, 46.419814867238614], [9.24528728687822, 46.43122301580838], [9.267712349891484, 46.45402638878749], [9.268306742510424, 46.473039969737094], [9.287839513754191, 46.49014088395138], [9.3587594729048, 46.50150702899981], [9.382412528354536, 46.47677483408487], [9.401113149931785, 46.46725673496972], [9.44005981389553, 46.49765584720837], [9.46395062639284, 46.48052908467327], [9.462524084107384, 46.43489649039423], [9.467833153551231, 46.4310905431642], [9.46664436831335, 46.393063381265], [9.471477923662045, 46.37404656927529], [9.490059666715508, 46.36072575397022], [9.51719940655368, 46.36070959876971], [9.539148955471793, 46.36830210698914], [9.578095619435537, 46.39870121922779], [9.611138821336496, 46.41389269774686], [9.643825387666089, 46.417676027696174], [9.708247492134975, 46.39482095807543], [9.732138304632283, 46.37769419554033], [9.742280929424824, 46.3548714363206], [9.760862672478288, 46.34155062101552], [9.793430360284095, 46.34153123477491], [9.832020388676474, 46.3605221984438], [9.859279007038435, 46.364308759433214], [9.892322208939392, 46.379500237952286], [9.924771018221412, 46.37567813552175], [9.95202963658337, 46.379464696511164], [9.984002931770238, 46.36043172932096], [10.00028677567314, 46.360422036200646], [10.0333299775741, 46.37561351471972], [10.063956401800711, 46.40031339923364], [10.05947948202338, 46.430738359793104], [10.038362082771783, 46.449764864903116], [10.041215167342694, 46.541030053461206], [10.091730998384433, 46.594239000759174], [10.097872217494796, 46.61705206685859], [10.111620405199563, 46.62274806354322], [10.193277381761657, 46.63030503032153], [10.226320583662615, 46.6454965088406], [10.25033027468371, 46.63217246249542], [10.254569437413465, 46.59414206955611], [10.284125954925985, 46.58461750836075], [10.310671302145218, 46.56558777221064], [10.42465820946554, 46.5655199203685], [10.45698814022377, 46.55789510174805], [10.471092963499903, 46.57499924700244], [10.478066332276779, 46.6244313264313], [10.467685950436662, 46.63964865327119], [10.432820363480298, 46.65297916169657], [10.400252675674489, 46.65299854793719], [10.386980002064874, 46.66251341601224], [10.371528307828486, 46.68914212246199], [10.377550648415061, 46.70815247237149], [10.399856832904538, 46.72715312916068], [10.39526103460342, 46.753775373530225], [10.422995167060531, 46.772772799279316], [10.413328056363142, 46.81080642325873], [10.43551536232883, 46.826004363858004], [10.452750234422039, 46.85641640025706], [10.454533412278858, 46.913457143105866], [10.466221457880643, 46.9400696943551], [10.46126902400816, 46.95528379015489], [10.442687280954699, 46.96860460545996], [10.421094367607948, 46.97242024581029], [10.389596586516232, 47.00666407776019], [10.357028898710427, 47.0066834640008], [10.332187058022814, 46.99338849701653], [10.30964311648576, 46.9667824078475], [10.3035018973754, 46.94396934174807], [10.284206883179209, 46.93447385991363], [10.246330125929555, 46.93829919338427], [10.232463059701, 46.92880048050972], [10.225727447971698, 46.886973833460694], [10.162533335939282, 46.86229333518738], [10.097041324756303, 46.85092395909885], [10.075805046980918, 46.86614774801894], [10.054212133634168, 46.869963388369264], [10.00643050863955, 46.90421691343946], [9.952626543058358, 46.91946008860016], [9.92005885525255, 46.91947947484077], [9.887966681541897, 46.93470972584106], [9.864194747568376, 46.95563920456609], [9.864908018711104, 46.97845550170561], [9.876358307265312, 46.99746262057501], [9.865977925425195, 47.012679947414895], [9.84184935588031, 47.022201277570154], [9.820018685485985, 47.01841148554064], [9.761024528984734, 47.041263324121275], [9.706863927832178, 47.045098350712216], [9.674771754121522, 47.06032860171251], [9.609517499986124, 47.056564658003815], [9.596482583424084, 47.073684958458706], [9.61312306289835, 47.085083413908166], [9.619264282008713, 47.10789648000758], [9.61478736223138, 47.138321440567054], [9.561934424840492, 47.18398634524711], [9.568075643950854, 47.20679941134653], [9.546958244699256, 47.22582591645654], [9.547671515841985, 47.248642213596064], [9.52124504714654, 47.27147466593609], [9.549454693698804, 47.30568295644487], [9.577307704679704, 47.32848309838388], [9.594661455296698, 47.36269785097286], [9.649773084639557, 47.389284553901284], [9.634559147450746, 47.42351869273087], [9.63551017564105, 47.453940422250234], [9.600644588684684, 47.46727093067562], [9.56348110257776, 47.493912561285775], [9.54418608838157, 47.484417079451326], [9.54359169576263, 47.46540349850173], [9.524177803042651, 47.45210530047736], [9.421046791657597, 47.452166690239295], [9.398502850120545, 47.42556060107026], [9.355317023427045, 47.43319188177092], [9.31696475208224, 47.42180635048187], [9.240616844963995, 47.41044343647353], [9.20226457361919, 47.399057905184485], [9.153175284862906, 47.391481552165565], [9.03823734935228, 47.36112767448833], [8.961413928138882, 47.33455389572032], [8.906421177319809, 47.31176990898181], [8.835144582597835, 47.28899561536362], [8.738669511616882, 47.241518206191394], [8.740967410767443, 47.22820708400663], [8.800674838411421, 47.228171542565505], [8.832767012122074, 47.21294129156521], [8.865334699927882, 47.21292190532459], [8.873060547046075, 47.19960755209972], [8.853765532849886, 47.19011207026528], [8.821197845044079, 47.19013145650589], [8.794414740777272, 47.20155576027616], [8.723732538674234, 47.19779504760756], [8.697068312931215, 47.21302206756775], [8.675475399584466, 47.21683770791808], [8.587439446864435, 47.17886224266051], [8.538112401060575, 47.16368045726174], [8.518698508340597, 47.150382259237375], [8.500988122152236, 47.10475935807864], [8.527295712323895, 47.07812418954869], [8.52693907675253, 47.066716040978925], [8.507762941080127, 47.0610232753344], [8.483753250059031, 47.074347321679575], [8.479514087329276, 47.11237771461889], [8.45597991040333, 47.14091262572374], [8.417746517582314, 47.133329810624616], [8.409188520797604, 47.12002515052005], [8.424996850605355, 47.104804592640065], [8.423926943891264, 47.07058014693078], [8.410059877662707, 47.061081434056234], [8.220081698795504, 47.0611945204598], [8.200667806075526, 47.047896322435435], [8.199954534932798, 47.02508002529591], [8.186087468704244, 47.01558131242137], [7.958113654063598, 47.01571701610564], [7.903358660292102, 47.00053846174697], [7.876100041930142, 46.996751900757566], [7.771780245307209, 46.9587861286203], [7.738974800453826, 46.95120008248107], [7.5030765888460005, 46.871481977217115], [7.491982935863155, 46.863883006917476], [7.415159514649758, 46.83730922814946], [7.387544260716434, 46.82211451859029], [7.316148787470672, 46.795537508782175], [7.266583984619234, 46.77275029100356], [7.194594118754532, 46.72715970024584], [7.144910437379306, 46.70056976627732], [7.072801692990816, 46.651176459329676], [7.067373745023181, 46.65117969036978], [6.975851107914712, 46.58848818539777], [6.925573033920547, 46.54288467047965], [6.897244508844496, 46.50487366378095], [6.8861508558616515, 46.497274693481316], [6.8466097992789665, 46.44786200029306], [6.854097889349585, 46.426942214688346], [6.897045958995508, 46.411705501607855], [6.920817892969029, 46.39077602288283], [6.901166243201475, 46.36987239247863], [6.863170607428034, 46.36989500975934], [6.814081318671748, 46.36231865674041], [6.778026946477503, 46.337622003266596], [6.777432553858564, 46.31860842231699], [6.793240883666315, 46.303387864437006], [6.856949716992473, 46.25771649767673], [6.85080849788211, 46.234903431577315], [6.8174086604097885, 46.20830380448848], [6.794626961825159, 46.17409228293961], [6.799579395697641, 46.15887818713982], [6.782225645080647, 46.12466343455085], [6.806116457577955, 46.10753667201575], [6.833256197416127, 46.10752051681524], [6.884286749751609, 46.09037759907963], [6.866219727991886, 46.03334654935113], [6.885039228092924, 46.0276311664259], [6.917844672946306, 46.03521721256513], [6.968043075615272, 45.99145528150007], [6.973114388011543, 45.980043901890205], [7.004968804674621, 45.957208218510075], [7.009683481499527, 45.93438869033045], [7.040467991448516, 45.877328561241036], [7.074620307262153, 45.841181755676125], [7.096213220608902, 45.83736611532581], [7.13444661342992, 45.844948930424934], [7.16677654418815, 45.83732411180448]]]}}, {"type": "Feature", "properties": {"date": "23.03.2002", "danger_level": 3, "url": "https://www.slf.ch/fileadmin/user_upload/import/lwdarchiv/public/2002/nbk/de/gif/20020323_nbk_de_c.gif"}, "geometry": {"type": "Polygon", "coordinates": [[[8.92214983580236, 47.20718390511865], [8.92214983580236, 47.20718390511865]]]}}, {"type": "Feature", "properties": {"date": "23.03.2002", "danger_level": 3, "url": "https://www.slf.ch/fileadmin/user_upload/import/lwdarchiv/public/2002/nbk/de/gif/20020323_nbk_de_c.gif"}, "geometry": {"type": "Polygon", "coordinates": [[[9.493113814991453, 47.0661409158408], [9.493113814991453, 47.0661409158408]]]}}, {"type": "Feature", "properties": {"date": "23.03.2002", "danger_level": 3, "url": "https://www.slf.ch/fileadmin/user_upload/import/lwdarchiv/public/2002/nbk/de/gif/20020323_nbk_de_c.gif"}, "geometry": {"type": "Polygon", "coordinates": [[[8.605067647871547, 46.614137886696675], [8.605067647871547, 46.614137886696675]]]}}]}