{"type": "FeatureCollection", "features": [{"type": "Feature", "properties": {"date": "20.03.2006", "danger_level": 2, "url": "https://www.slf.ch/fileadmin/user_upload/import/lwdarchiv/public/2006/nbk/fr/gif/20060320_nbk_fr_c.gif"}, "geometry": {"type": "Polygon", "coordinates": [[[9.6105933253924, 47.11991056977807], [9.6105933253924, 47.11991056977807]]]}}, {"type": "Feature", "properties": {"date": "20.03.2006", "danger_level": 2, "url": "https://www.slf.ch/fileadmin/user_upload/import/lwdarchiv/public/2006/nbk/fr/gif/20060320_nbk_fr_c.gif"}, "geometry": {"type": "Polygon", "coordinates": [[[8.4227374430272, 47.09688878338686], [8.4227374430272, 47.09688878338686]]]}}, {"type": "Feature", "properties": {"date": "20.03.2006", "danger_level": 2, "url": "https://www.slf.ch/fileadmin/user_upload/import/lwdarchiv/public/2006/nbk/fr/gif/20060320_nbk_fr_c.gif"}, "geometry": {"type": "Polygon", "coordinates": [[[9.594026367115742, 47.062495030051785], [9.594026367115742, 47.062495030051785]]]}}, {"type": "Feature", "properties": {"date": "20.03.2006", "danger_level": 2, "url": "https://www.slf.ch/fileadmin/user_upload/import/lwdarchiv/public/2006/nbk/fr/gif/20060320_nbk_fr_c.gif"}, "geometry": {"type": "Polygon", "coordinates": [[[9.86266378720271, 46.99261201653988], [9.86266378720271, 46.99261201653988]]]}}, {"type": "Feature", "properties": {"date": "20.03.2006", "danger_level": 2, "url": "https://www.slf.ch/fileadmin/user_upload/import/lwdarchiv/public/2006/nbk/fr/gif/20060320_nbk_fr_c.gif"}, "geometry": {"type": "Polygon", "coordinates": [[[9.861822995859784, 46.961236773073004], [9.861822995859784, 46.961236773073004]]]}}, {"type": "Feature", "properties": {"date": "20.03.2006", "danger_level": 2, "url": "https://www.slf.ch/fileadmin/user_upload/import/lwdarchiv/public/2006/nbk/fr/gif/20060320_nbk_fr_c.gif"}, "geometry": {"type": "Polygon", "coordinates": [[[8.592027481799903, 46.9649425927006], [8.592027481799903, 46.9649425927006]]]}}, {"type": "Feature", "properties": {"date": "20.03.2006", "danger_level": 2, "url": "https://www.slf.ch/fileadmin/user_upload/import/lwdarchiv/public/2006/nbk/fr/gif/20060320_nbk_fr_c.gif"}, "geometry": {"type": "Polygon", "coordinates": [[[10.281696413993108, 46.92690081064261], [10.281696413993108, 46.92690081064261]]]}}, {"type": "Feature", "properties": {"date": "20.03.2006", "danger_level": 2, "url": "https://www.slf.ch/fileadmin/user_upload/import/lwdarchiv/public/2006/nbk/fr/gif/20060320_nbk_fr_c.gif"}, "geometry": {"type": "Polygon", "coordinates": [[[10.228266346465652, 46.89589565704618], [10.228266346465652, 46.89589565704618]]]}}, {"type": "Feature", "properties": {"date": "20.03.2006", "danger_level": 2, "url": "https://www.slf.ch/fileadmin/user_upload/import/lwdarchiv/public/2006/nbk/fr/gif/20060320_nbk_fr_c.gif"}, "geometry": {"type": "Polygon", "coordinates": [[[9.559070735986092, 46.87968425642101], [9.55921086787658, 46.88491346366549], [9.50662159169205, 46.885283553535935], [9.506481459801561, 46.88005434629145], [9.559070735986092, 46.87968425642101]]]}}, {"type": "Feature", "properties": {"date": "20.03.2006", "danger_level": 2, "url": "https://www.slf.ch/fileadmin/user_upload/import/lwdarchiv/public/2006/nbk/fr/gif/20060320_nbk_fr_c.gif"}, "geometry": {"type": "Polygon", "coordinates": [[[10.114173721451067, 46.84439663432377], [10.114173721451067, 46.84439663432377]]]}}, {"type": "Feature", "properties": {"date": "20.03.2006", "danger_level": 2, "url": "https://www.slf.ch/fileadmin/user_upload/import/lwdarchiv/public/2006/nbk/fr/gif/20060320_nbk_fr_c.gif"}, "geometry": {"type": "Polygon", "coordinates": [[[10.420234778350784, 46.76902006365992], [10.420234778350784, 46.76902006365992]]]}}, {"type": "Feature", "properties": {"date": "20.03.2006", "danger_level": 2, "url": "https://www.slf.ch/fileadmin/user_upload/import/lwdarchiv/public/2006/nbk/fr/gif/20060320_nbk_fr_c.gif"}, "geometry": {"type": "Polygon", "coordinates": [[[10.444540385803387, 46.554411086710346], [10.471185353621872, 46.56729905988632], [10.472726804417233, 46.62482033957558], [10.446922627941674, 46.643307609866476], [10.401986237388277, 46.6488540369999], [10.387240993687957, 46.65941819145184], [10.375621533350769, 46.64642447831288], [10.287613348592718, 46.58689659978853], [10.268761398295855, 46.584414171120024], [10.30959108225271, 46.56582116086614], [10.414769634621774, 46.56508098112526], [10.444540385803387, 46.554411086710346]]]}}, {"type": "Feature", "properties": {"date": "20.03.2006", "danger_level": 2, "url": "https://www.slf.ch/fileadmin/user_upload/import/lwdarchiv/public/2006/nbk/fr/gif/20060320_nbk_fr_c.gif"}, "geometry": {"type": "Polygon", "coordinates": [[[8.606017697702109, 46.64580234084294], [8.606017697702109, 46.64580234084294]]]}}, {"type": "Feature", "properties": {"date": "20.03.2006", "danger_level": 2, "url": "https://www.slf.ch/fileadmin/user_upload/import/lwdarchiv/public/2006/nbk/fr/gif/20060320_nbk_fr_c.gif"}, "geometry": {"type": "Polygon", "coordinates": [[[10.236285259422573, 46.63432955485928], [10.236285259422573, 46.63432955485928]]]}}, {"type": "Feature", "properties": {"date": "20.03.2006", "danger_level": 2, "url": "https://www.slf.ch/fileadmin/user_upload/import/lwdarchiv/public/2006/nbk/fr/gif/20060320_nbk_fr_c.gif"}, "geometry": {"type": "Polygon", "coordinates": [[[10.183415719457068, 46.624241230240756], [10.183415719457068, 46.624241230240756]]]}}, {"type": "Feature", "properties": {"date": "20.03.2006", "danger_level": 2, "url": "https://www.slf.ch/fileadmin/user_upload/import/lwdarchiv/public/2006/nbk/fr/gif/20060320_nbk_fr_c.gif"}, "geometry": {"type": "Polygon", "coordinates": [[[10.138199065122697, 46.619329242885236], [10.138199065122697, 46.619329242885236]]]}}, {"type": "Feature", "properties": {"date": "20.03.2006", "danger_level": 2, "url": "https://www.slf.ch/fileadmin/user_upload/import/lwdarchiv/public/2006/nbk/fr/gif/20060320_nbk_fr_c.gif"}, "geometry": {"type": "Polygon", "coordinates": [[[9.783838452297886, 46.574751266815035], [9.783838452297886, 46.574751266815035]]]}}, {"type": "Feature", "properties": {"date": "20.03.2006", "danger_level": 2, "url": "https://www.slf.ch/fileadmin/user_upload/import/lwdarchiv/public/2006/nbk/fr/gif/20060320_nbk_fr_c.gif"}, "geometry": {"type": "Polygon", "coordinates": [[[9.843940482223065, 46.5743283069631], [9.843940482223065, 46.5743283069631]]]}}, {"type": "Feature", "properties": {"date": "20.03.2006", "danger_level": 2, "url": "https://www.slf.ch/fileadmin/user_upload/import/lwdarchiv/public/2006/nbk/fr/gif/20060320_nbk_fr_c.gif"}, "geometry": {"type": "Polygon", "coordinates": [[[10.037590496794046, 46.510203200510574], [10.037590496794046, 46.510203200510574]]]}}, {"type": "Feature", "properties": {"date": "20.03.2006", "danger_level": 2, "url": "https://www.slf.ch/fileadmin/user_upload/import/lwdarchiv/public/2006/nbk/fr/gif/20060320_nbk_fr_c.gif"}, "geometry": {"type": "Polygon", "coordinates": [[[9.857424538908997, 46.51670128731085], [9.857424538908997, 46.51670128731085]]]}}, {"type": "Feature", "properties": {"date": "20.03.2006", "danger_level": 2, "url": "https://www.slf.ch/fileadmin/user_upload/import/lwdarchiv/public/2006/nbk/fr/gif/20060320_nbk_fr_c.gif"}, "geometry": {"type": "Polygon", "coordinates": [[[9.451035177461605, 46.493410230089005], [9.451035177461605, 46.493410230089005]]]}}, {"type": "Feature", "properties": {"date": "20.03.2006", "danger_level": 2, "url": "https://www.slf.ch/fileadmin/user_upload/import/lwdarchiv/public/2006/nbk/fr/gif/20060320_nbk_fr_c.gif"}, "geometry": {"type": "Polygon", "coordinates": [[[9.464799497928515, 46.44624162492571], [9.469326600196519, 46.4749758297796], [9.461813846455872, 46.47502869976109], [9.464799497928515, 46.44624162492571]]]}}, {"type": "Feature", "properties": {"date": "20.03.2006", "danger_level": 2, "url": "https://www.slf.ch/fileadmin/user_upload/import/lwdarchiv/public/2006/nbk/fr/gif/20060320_nbk_fr_c.gif"}, "geometry": {"type": "Polygon", "coordinates": [[[9.01210382222199, 45.81657400727034], [9.038748790040474, 45.82946198044632], [9.039029053821448, 45.83992039493527], [9.070060992017448, 45.876313365720655], [9.070481387688911, 45.89200098745409], [9.029651703732057, 45.91059399770797], [8.996895301077801, 45.950050966958266], [8.959751928046026, 45.96600293859916], [8.971511520273705, 45.9842258589826], [8.994049781495645, 45.98406724903812], [9.013462259354457, 46.007466506684544], [9.00651003317576, 46.028436205643956], [9.040948018515866, 46.05172972332739], [9.075105740074996, 46.064564826521874], [9.076226795198895, 46.1063984844777], [9.129656862726353, 46.13740363807413], [9.145242897769597, 46.15821472708906], [9.145803425331547, 46.17913155606698], [9.157422885668737, 46.19212526920594], [9.187614032521815, 46.19714299652445], [9.229564771602567, 46.2203836442264], [9.24515080664581, 46.24119473324133], [9.253364219838897, 46.26728789948223], [9.284396158034896, 46.30368087026761], [9.292609571227983, 46.32977403650851], [9.270912101348964, 46.36130788991986], [9.271893024582377, 46.3979123406312], [9.260974223697625, 46.41106466371464], [9.256727385210596, 46.39278887334971], [9.200031402429522, 46.3801123800997], [9.06480183509787, 46.38106403976655], [8.99009469336286, 46.3972803613149], [8.952951320331085, 46.41323233295579], [8.856826972498032, 46.47144092240445], [8.826916089425929, 46.47688160957489], [8.766814059500751, 46.47730456942682], [8.72897002701654, 46.46711050484532], [8.683753372682169, 46.46219851748979], [8.638676850238285, 46.46251573737874], [8.608485703385208, 46.457498010060235], [8.562988785269862, 46.44212760821575], [8.509558717742408, 46.41112245461931], [8.468028374333116, 46.4035694286508], [8.465786264085315, 46.31990211273914], [8.44240721152045, 46.28868547921675], [8.463544153837516, 46.23623479682749], [8.504373837794372, 46.217641786573616], [8.55966850167057, 46.178026207378835], [8.589018857180722, 46.151668691230476], [8.61071632705974, 46.12013483781914], [8.688969647829342, 46.09604827041332], [8.750192732878421, 46.137458968517215], [8.765218240359715, 46.13735322855423], [8.807309111330957, 46.16582308350066], [8.804043196077338, 46.18415174384708], [8.676326382486334, 46.18505053353243], [8.650522206010775, 46.20353780382333], [8.65873561920386, 46.229630970064235], [8.677727701391209, 46.23734260597722], [8.89559755986998, 46.23580937651397], [8.92140173634554, 46.21732210622307], [8.913188323152454, 46.19122893998217], [8.894196240965105, 46.183517304069184], [8.819068703558631, 46.1840460038841], [8.814821865071604, 46.165770213519174], [8.844592616253218, 46.15510031910425], [8.844172220581756, 46.139412697370815], [8.7907421530543, 46.108407543774376], [8.790321757382838, 46.09271992204094], [8.82391895138002, 46.084638196257515], [8.849723127855578, 46.06615092596662], [8.856815485924763, 46.050410434251695], [8.841229450881519, 46.02959934523677], [8.810477776466492, 46.00366478894034], [8.81005738079503, 45.98797716720691], [8.858119554711557, 45.95887287248258], [8.880657815933498, 45.9587142625381], [8.906041596737595, 45.92453937051377], [8.920786840437916, 45.913975216061836], [8.927458802835638, 45.88254710261347], [8.94206391464547, 45.866753740917055], [8.941363255193032, 45.84060770469466], [8.997078314740694, 45.81667974723332], [9.01210382222199, 45.81657400727034]]]}}, {"type": "Feature", "properties": {"date": "20.03.2006", "danger_level": 2, "url": "https://www.slf.ch/fileadmin/user_upload/import/lwdarchiv/public/2006/nbk/fr/gif/20060320_nbk_fr_c.gif"}, "geometry": {"type": "Polygon", "coordinates": [[[8.397708202975622, 46.44329074780856], [8.397708202975622, 46.44329074780856]]]}}, {"type": "Feature", "properties": {"date": "20.03.2006", "danger_level": 2, "url": "https://www.slf.ch/fileadmin/user_upload/import/lwdarchiv/public/2006/nbk/fr/gif/20060320_nbk_fr_c.gif"}, "geometry": {"type": "Polygon", "coordinates": [[[10.090125404632902, 46.22740304945681], [10.127829305226626, 46.23236790679383], [10.162127158676245, 46.25043221723279], [10.169920176197866, 46.26083776174026], [10.162967950019171, 46.28180746069967], [10.11873221891821, 46.313499924055485], [10.104267238998865, 46.33452249299638], [10.104687634670329, 46.35021011472981], [10.151165476019086, 46.40218496728565], [10.13301418517466, 46.425848574839534], [10.095450416471424, 46.42611292474699], [10.076458334284075, 46.418401288834], [10.076037938612613, 46.402713667100564], [10.033947067641373, 46.37424381215414], [9.995962903266674, 46.35882054032816], [10.005620517137038, 46.298605352044426], [10.046450201093892, 46.280012341790545], [10.064741623828805, 46.26157794148114], [10.064321228157342, 46.24589031974771], [10.090125404632902, 46.22740304945681]]]}}, {"type": "Feature", "properties": {"date": "20.03.2006", "danger_level": 2, "url": "https://www.slf.ch/fileadmin/user_upload/import/lwdarchiv/public/2006/nbk/fr/gif/20060320_nbk_fr_c.gif"}, "geometry": {"type": "Polygon", "coordinates": [[[9.913743007791014, 46.375089731858004], [9.913743007791014, 46.375089731858004]]]}}, {"type": "Feature", "properties": {"date": "20.03.2006", "danger_level": 2, "url": "https://www.slf.ch/fileadmin/user_upload/import/lwdarchiv/public/2006/nbk/fr/gif/20060320_nbk_fr_c.gif"}, "geometry": {"type": "Polygon", "coordinates": [[[6.900848494010472, 46.38583217994716], [6.900848494010472, 46.38583217994716]]]}}, {"type": "Feature", "properties": {"date": "20.03.2006", "danger_level": 2, "url": "https://www.slf.ch/fileadmin/user_upload/import/lwdarchiv/public/2006/nbk/fr/gif/20060320_nbk_fr_c.gif"}, "geometry": {"type": "Polygon", "coordinates": [[[9.755134387894497, 46.34482475800245], [9.755134387894497, 46.34482475800245]]]}}, {"type": "Feature", "properties": {"date": "20.03.2006", "danger_level": 2, "url": "https://www.slf.ch/fileadmin/user_upload/import/lwdarchiv/public/2006/nbk/fr/gif/20060320_nbk_fr_c.gif"}, "geometry": {"type": "Polygon", "coordinates": [[[8.168121634041581, 46.28800062991895], [8.168121634041581, 46.28800062991895]]]}}, {"type": "Feature", "properties": {"date": "20.03.2006", "danger_level": 2, "url": "https://www.slf.ch/fileadmin/user_upload/import/lwdarchiv/public/2006/nbk/fr/gif/20060320_nbk_fr_c.gif"}, "geometry": {"type": "Polygon", "coordinates": [[[6.859921559935537, 46.26059555598713], [6.859921559935537, 46.26059555598713]]]}}, {"type": "Feature", "properties": {"date": "20.03.2006", "danger_level": 2, "url": "https://www.slf.ch/fileadmin/user_upload/import/lwdarchiv/public/2006/nbk/fr/gif/20060320_nbk_fr_c.gif"}, "geometry": {"type": "Polygon", "coordinates": [[[8.149873093079073, 46.16783460325893], [8.149873093079073, 46.16783460325893]]]}}, {"type": "Feature", "properties": {"date": "20.03.2006", "danger_level": 2, "url": "https://www.slf.ch/fileadmin/user_upload/import/lwdarchiv/public/2006/nbk/fr/gif/20060320_nbk_fr_c.gif"}, "geometry": {"type": "Polygon", "coordinates": [[[7.505263353833092, 45.947472640173146], [7.505263353833092, 45.947472640173146]]]}}, {"type": "Feature", "properties": {"date": "20.03.2006", "danger_level": 2, "url": "https://www.slf.ch/fileadmin/user_upload/import/lwdarchiv/public/2006/nbk/fr/gif/20060320_nbk_fr_c.gif"}, "geometry": {"type": "Polygon", "coordinates": [[[7.857942383972054, 45.92930012930961], [7.857942383972054, 45.92930012930961]]]}}, {"type": "Feature", "properties": {"date": "20.03.2006", "danger_level": 2, "url": "https://www.slf.ch/fileadmin/user_upload/import/lwdarchiv/public/2006/nbk/fr/gif/20060320_nbk_fr_c.gif"}, "geometry": {"type": "Polygon", "coordinates": [[[8.95111811918148, 45.92422215062482], [8.95111811918148, 45.92422215062482]]]}}, {"type": "Feature", "properties": {"date": "20.03.2006", "danger_level": 2, "url": "https://www.slf.ch/fileadmin/user_upload/import/lwdarchiv/public/2006/nbk/fr/gif/20060320_nbk_fr_c.gif"}, "geometry": {"type": "Polygon", "coordinates": [[[7.752623699712504, 45.92481110180601], [7.752623699712504, 45.92481110180601]]]}}, {"type": "Feature", "properties": {"date": "20.03.2006", "danger_level": 2, "url": "https://www.slf.ch/fileadmin/user_upload/import/lwdarchiv/public/2006/nbk/fr/gif/20060320_nbk_fr_c.gif"}, "geometry": {"type": "Polygon", "coordinates": [[[7.323696077043171, 45.90167865452863], [7.323696077043171, 45.90167865452863]]]}}, {"type": "Feature", "properties": {"date": "20.03.2006", "danger_level": 2, "url": "https://www.slf.ch/fileadmin/user_upload/import/lwdarchiv/public/2006/nbk/fr/gif/20060320_nbk_fr_c.gif"}, "geometry": {"type": "Polygon", "coordinates": [[[7.112217917181146, 45.861325356054564], [7.112217917181146, 45.861325356054564]]]}}, {"type": "Feature", "properties": {"date": "20.03.2006", "danger_level": 2, "url": "https://www.slf.ch/fileadmin/user_upload/import/lwdarchiv/public/2006/nbk/fr/gif/20060320_nbk_fr_c.gif"}, "geometry": {"type": "Polygon", "coordinates": [[[7.172319947106325, 45.86090239620263], [7.172319947106325, 45.86090239620263]]]}}, {"type": "Feature", "properties": {"date": "20.03.2006", "danger_level": 3, "url": "https://www.slf.ch/fileadmin/user_upload/import/lwdarchiv/public/2006/nbk/fr/gif/20060320_nbk_fr_c.gif"}, "geometry": {"type": "Polygon", "coordinates": [[[7.0971924096998515, 45.86143109601755], [7.104845295330986, 45.86660743328054], [7.179972832737459, 45.86607873346563], [7.1952786039997285, 45.8764314079916], [7.248288275855723, 45.891748939854594], [7.286272440230421, 45.907172211680574], [7.376145221337214, 45.89607935741372], [7.406476500080778, 45.906326291976704], [7.4447409282364525, 45.93220797829164], [7.543527781988766, 45.97335432648808], [7.573578796951356, 45.97314284656211], [7.595836794392323, 45.96252582212868], [7.655938824317501, 45.96210286227675], [7.6928019335683, 45.9356924761469], [7.730085438490562, 45.92496971175048], [7.752763831602992, 45.93004030905049], [7.789907204634765, 45.914088337409595], [7.834983727078649, 45.913771117520646], [7.854115941156486, 45.92671196067811], [7.86232935434957, 45.95280512691901], [7.877775257502328, 45.96838700868946], [7.912073110951946, 45.98645131912843], [7.957149633395831, 45.98613409923948], [7.972315272767613, 45.99125756652097], [8.014686407519827, 46.03018583595635], [8.01566733075324, 46.066790286667704], [8.042592562352699, 46.09013667433263], [8.080436594836911, 46.10033073891414], [8.110908005470963, 46.11580688072161], [8.145486122701557, 46.14432960564953], [8.153559404004154, 46.165193564645946], [8.124769576055952, 46.21246790977222], [8.08804659869564, 46.24410750314655], [8.088466994367101, 46.259795124879986], [8.130557865338345, 46.28826497982641], [8.183287273413361, 46.29312409720045], [8.244650490352926, 46.33976400254882], [8.301766868805462, 46.368128117532265], [8.295235038298229, 46.404785438225105], [8.329673023638334, 46.428078955908546], [8.382822827384816, 46.44862569501602], [8.443064989200481, 46.453431942408564], [8.468729033785552, 46.42971546487319], [8.47936757088933, 46.4061047273008], [8.509558717742408, 46.41112245461931], [8.562988785269862, 46.44212760821575], [8.608485703385208, 46.457498010060235], [8.638676850238285, 46.46251573737874], [8.683753372682169, 46.46219851748979], [8.72897002701654, 46.46711050484532], [8.766814059500751, 46.47730456942682], [8.826916089425929, 46.47688160957489], [8.856826972498032, 46.47144092240445], [8.952951320331085, 46.41323233295579], [8.99009469336286, 46.3972803613149], [9.06480183509787, 46.38106403976655], [9.200031402429522, 46.3801123800997], [9.256727385210596, 46.39278887334971], [9.250475818484334, 46.439904608531506], [9.26606185352758, 46.46071569754644], [9.266482249199042, 46.476403319279875], [9.308432988279794, 46.49964396698182], [9.35350951072368, 46.49932674709287], [9.390512751864966, 46.4781455682075], [9.40553825934626, 46.47803982824452], [9.4361498018708, 46.49874517729646], [9.451175309352093, 46.49863943733348], [9.469326600196519, 46.4749758297796], [9.460973055112946, 46.44365345629422], [9.460132263770022, 46.412278212827346], [9.47431697990839, 46.380797229397494], [9.511039957268704, 46.34915763602317], [9.518132315337889, 46.33341714430824], [9.558681735513767, 46.3043657195654], [9.59596524043603, 46.293642955169], [9.640901630989426, 46.28809652803557], [9.671232909732991, 46.29834346259856], [9.693771170954932, 46.29818485265408], [9.712903385032767, 46.31112569581155], [9.713463912594719, 46.332042524789465], [9.74024901230369, 46.35015970520992], [9.792698156597734, 46.344560408095], [9.838335206603567, 46.36516001718397], [9.87603910719729, 46.37012487452098], [9.898857632200208, 46.38042467906546], [9.951446908384739, 46.380054589195026], [9.995962903266674, 46.35882054032816], [10.033947067641373, 46.37424381215414], [10.076037938612613, 46.402713667100564], [10.076598466174563, 46.42363049607848], [10.039455093142788, 46.439582467719376], [10.041276807719125, 46.507562161897596], [10.03418444964994, 46.52330265361252], [10.065496651626916, 46.570154038886855], [10.080802422889187, 46.58050671341283], [10.088875704191784, 46.60137067240925], [10.130826443272538, 46.6246113201112], [10.168390211975774, 46.62434697020374], [10.23642539131306, 46.63955876210376], [10.25485694593846, 46.626353569038834], [10.254016154595536, 46.594978325571965], [10.287613348592718, 46.58689659978853], [10.375621533350769, 46.64642447831288], [10.383554682762878, 46.66205923006483], [10.369089702843533, 46.68308179900572], [10.392608887298888, 46.71952763977259], [10.393169414860838, 46.7404444687505], [10.416408335535218, 46.766431895028425], [10.417529390659118, 46.80826555298425], [10.448561328855117, 46.84465852376964], [10.450242911540967, 46.907409010703375], [10.466109210365184, 46.93867851420727], [10.432792280148979, 46.95721865447965], [10.373811305347699, 46.999475272287405], [10.358785797866405, 46.99958101225039], [10.3243478125263, 46.97628749456695], [10.30848151370208, 46.94501799106307], [10.281696413993108, 46.92690081064261], [10.259298284661654, 46.93228862783156], [10.23265331684317, 46.91940065465559], [10.231812525500246, 46.88802541118872], [10.19737454016014, 46.86473189350528], [10.144364868304145, 46.84941436164228], [10.10666096771042, 46.84444950430526], [10.062004840938, 46.86045434592764], [10.002883734246232, 46.897481756490926], [9.950714853733164, 46.913539468094804], [9.905778463179768, 46.91908589522823], [9.86522904300389, 46.94813731997107], [9.858136684934703, 46.96387781168599], [9.86635009812779, 46.989970977926895], [9.859257740058602, 47.00571146964182], [9.818147792320776, 47.01384606540674], [9.758606289957546, 47.03518585423659], [9.728555274994957, 47.03539733416255], [9.70629727755399, 47.04601435859598], [9.646475511409788, 47.05689573293687], [9.623797118297357, 47.05182513563687], [9.601398988965903, 47.05721295282582], [9.59048018808115, 47.07036527590925], [9.61357897686504, 47.09112349494269], [9.614279636317479, 47.117269531165086], [9.592582166438463, 47.14880338457643], [9.563091679037823, 47.169931693480315], [9.563932470380747, 47.201306936947184], [9.549607622351889, 47.22755871313256], [9.520397398732225, 47.259145436525394], [9.52861081192531, 47.28523860276629], [9.567015371971472, 47.31634949632571], [9.582741538905202, 47.34238979258512], [9.572103001801425, 47.3660005301575], [9.534819496879162, 47.37672329455392], [9.459691959472691, 47.377251994368834], [9.452039073841558, 47.372075657105846], [9.376631272654109, 47.36214594243181], [9.353812747651192, 47.35184613788732], [9.300943207685686, 47.341757813268806], [9.247793403939205, 47.32121107416134], [9.157079831489487, 47.30092868496132], [9.088764388371223, 47.27525847857235], [9.050920355887014, 47.26506441399086], [8.944340484613075, 47.21351252128695], [8.89884356649773, 47.198142119442466], [8.861139665904005, 47.19317726210544], [8.83832114090109, 47.18287745756096], [8.74774770034186, 47.16782427560542], [8.717416421598294, 47.15757734104243], [8.626842981039065, 47.1425241590869], [8.536409672370322, 47.13270018437584], [8.502111818920705, 47.11463587393688], [8.516576798840049, 47.09361330499598], [8.504677074721883, 47.070161177368064], [8.486105388205996, 47.07813716318851], [8.468374493033034, 47.11748839247583], [8.44597636370158, 47.12287620966478], [8.418770868321145, 47.08907140751089], [8.426143490171306, 47.08378933028492], [8.399358390462336, 47.06567214986447], [8.204026793205506, 47.067046769383246], [8.184894579127668, 47.05410592622578], [8.172994855009502, 47.03065379859786], [8.157829215637722, 47.02553033131637], [7.970010372121538, 47.02685208085366], [7.924513454006193, 47.01148167900917], [7.8641311603000394, 47.001446224372145], [7.765484438438212, 46.96552908342019], [7.674630734098008, 46.9400174869757], [7.553165487233263, 46.89380054147925], [7.522974340380187, 46.88878281416074], [7.462311782893058, 46.868288945034756], [7.409021847256089, 46.842512998682814], [7.386343454143661, 46.83744240138281], [7.333053518506692, 46.81166645503085], [7.310375125394263, 46.806595857730855], [7.257085189757294, 46.7808199113789], [7.20351499033935, 46.744585550538], [7.150225054702383, 46.71880960418604], [7.043084655866497, 46.64634088250423], [7.035571902125849, 46.646393752485714], [6.993481031154608, 46.61792389753929], [6.955076471108447, 46.58681300397988], [6.924184664802933, 46.555649240438974], [6.900665480347579, 46.5192033996721], [6.846534753367686, 46.46205220985328], [6.872198797952757, 46.43833573231791], [6.894596927284212, 46.43294791512895], [6.9204011037597715, 46.41446064483806], [6.91998070808831, 46.398773023104624], [6.900848494010472, 46.38583217994716], [6.833233710344647, 46.38630800978058], [6.799075988785515, 46.373472906586095], [6.78348995374227, 46.35266181757117], [6.790442179920968, 46.331692118611755], [6.856795776572406, 46.28415342357803], [6.8637480027511035, 46.26318372461863], [6.8097574076616985, 46.211261742044286], [6.801684126359101, 46.19039778304786], [6.800282807454226, 46.13810571060308], [6.818854493970114, 46.130129724782634], [6.848905508932703, 46.12991824485667], [6.878676260114317, 46.119248350441744], [6.88959506099907, 46.106096027358305], [6.881802043477447, 46.09569048285085], [6.880961252134522, 46.06431523938397], [6.892020184909763, 46.05639212354502], [6.929583953612999, 46.056127773637556], [6.955107866307584, 46.02718208885771], [7.006576087368216, 45.98497834103144], [7.021041067287561, 45.96395577209054], [7.056642989523972, 45.890482520760386], [7.0971924096998515, 45.86143109601755]]]}}, {"type": "Feature", "properties": {"date": "20.03.2006", "danger_level": 3, "url": "https://www.slf.ch/fileadmin/user_upload/import/lwdarchiv/public/2006/nbk/fr/gif/20060320_nbk_fr_c.gif"}, "geometry": {"type": "Polygon", "coordinates": [[[8.59585392461547, 46.96753076133209], [8.59585392461547, 46.96753076133209]]]}}]}